{"E00023433": {"ChIJY_VpIZcadkgRUgZB5SFOuEI": {"geometry": {"location": {"lat": 51.54009365000683, "lng": -0.1737775001802353}, "viewport": {"northeast": {"lat": 51.5414426302915, "lng": -0.172428519708498}, "southwest": {"lat": 51.5387446697085, "lng": -0.175126480291502}}}, "name": "2-4 St John's Wood Park", "place_id": "ChIJY_VpIZcadkgRUgZB5SFOuEI", "types": ["route"]}, "ChIJhQM_I5cadkgRZqIiW9shw_I": {"geometry": {"location": {"lat": 51.5397297, "lng": -0.1732535}, "viewport": {"northeast": {"lat": 51.5410596302915, "lng": -0.171967119708498}, "southwest": {"lat": 51.5383616697085, "lng": -0.174665080291502}}}, "name": "Compass Creatives", "place_id": "ChIJhQM_I5cadkgRZqIiW9shw_I", "types": ["point_of_interest", "establishment"]}, "ChIJf48sGZcadkgRTQ1_CboTuZE": {"geometry": {"location": {"lat": 51.53966459999999, "lng": -0.1738608}, "viewport": {"northeast": {"lat": 51.54101358029149, "lng": -0.1725118197084979}, "southwest": {"lat": 51.5383156197085, "lng": -0.175209780291502}}}, "name": "The Lacrosse Foundation", "place_id": "ChIJf48sGZcadkgRTQ1_CboTuZE", "types": ["point_of_interest", "establishment"]}, "ChIJYxjqBJcadkgR8lPI_QjgHZY": {"geometry": {"location": {"lat": 51.53911927236216, "lng": -0.1739629600911594}, "viewport": {"northeast": {"lat": 51.5404683302915, "lng": -0.172615169708498}, "southwest": {"lat": 51.5377703697085, "lng": -0.175313130291502}}}, "name": "8-20 St John's Wood Park", "place_id": "ChIJYxjqBJcadkgR8lPI_QjgHZY", "types": ["route"]}, "ChIJxzsFHJcadkgR9Fq_8kLEHCU": {"geometry": {"location": {"lat": 51.5394891, "lng": -0.1738081}, "viewport": {"northeast": {"lat": 51.54084118029149, "lng": -0.172501719708498}, "southwest": {"lat": 51.53814321970849, "lng": -0.175199680291502}}}, "name": "ubitricity Charging Station", "place_id": "ChIJxzsFHJcadkgR9Fq_8kLEHCU", "types": ["point_of_interest", "establishment"]}, "ChIJG3_lrZcadkgR9GbLFR9RPXk": {"geometry": {"location": {"lat": 51.53792113128873, "lng": -0.1738227149443028}, "viewport": {"northeast": {"lat": 51.5392800802915, "lng": -0.172446569708498}, "southwest": {"lat": 51.53658211970851, "lng": -0.175144530291502}}}, "name": "30 St John's Wood Park", "place_id": "ChIJG3_lrZcadkgR9GbLFR9RPXk", "types": ["route"]}, "ChIJbayfoywFdkgRc7oo6W1Tk_4": {"geometry": {"location": {"lat": 51.5378031, "lng": -0.1736776}, "viewport": {"northeast": {"lat": 51.5391713802915, "lng": -0.172288619708498}, "southwest": {"lat": 51.5364734197085, "lng": -0.174986580291502}}}, "name": "Yellow Brick Capital (UK) Limited", "place_id": "ChIJbayfoywFdkgRc7oo6W1Tk_4", "types": ["finance", "point_of_interest", "establishment"], "rating": 5, "user_ratings_total": 1}, "ChIJt4f_oywFdkgR6Bc0fGHDkZw": {"geometry": {"location": {"lat": 51.53823019999999, "lng": -0.1738063}, "viewport": {"northeast": {"lat": 51.5395456802915, "lng": -0.172593419708498}, "southwest": {"lat": 51.5368477197085, "lng": -0.175291380291502}}}, "name": "Yellow Brick Estates", "place_id": "ChIJt4f_oywFdkgR6Bc0fGHDkZw", "types": ["finance", "point_of_interest", "establishment"]}, "ChIJSRNvNK8bdkgRTP3Uey11CRk": {"geometry": {"location": {"lat": 51.53787899999999, "lng": -0.1733911}, "viewport": {"northeast": {"lat": 51.53917118029149, "lng": -0.171970619708498}, "southwest": {"lat": 51.53647321970849, "lng": -0.174668580291502}}}, "name": "zero waste management", "place_id": "ChIJSRNvNK8bdkgRTP3Uey11CRk", "types": ["point_of_interest", "establishment"]}, "ChIJ_SJsLFkbdkgR6Gz0zTDpHLI": {"geometry": {"location": {"lat": 51.53796450000001, "lng": -0.1743739}, "viewport": {"northeast": {"lat": 51.5393750802915, "lng": -0.172846719708498}, "southwest": {"lat": 51.5366771197085, "lng": -0.175544680291502}}}, "name": "25 St. John Wood Park", "place_id": "ChIJ_SJsLFkbdkgR6Gz0zTDpHLI", "types": ["lodging", "point_of_interest", "establishment"]}, "ChIJs7F1uJcadkgRBD8nE1ga1uM": {"geometry": {"location": {"lat": 51.53725082394085, "lng": -0.1742995097224455}, "viewport": {"northeast": {"lat": 51.5385996802915, "lng": -0.17266925}, "southwest": {"lat": 51.5359017197085, "lng": -0.17592945}}}, "name": "22-1 Queen's Grove", "place_id": "ChIJs7F1uJcadkgRBD8nE1ga1uM", "types": ["route"]}, "ChIJCy3vQkgbdkgRVWL2wZ2XOKQ": {"geometry": {"location": {"lat": 51.5365587, "lng": -0.1731787}, "viewport": {"northeast": {"lat": 51.5380481302915, "lng": -0.171479469708498}, "southwest": {"lat": 51.53535016970851, "lng": -0.174177430291502}}}, "name": "THE OLD RIDING SCHOOL, ST JOHNS WOOD BARRACKS", "place_id": "ChIJCy3vQkgbdkgRVWL2wZ2XOKQ", "types": ["school", "point_of_interest", "establishment"]}, "ChIJ-2xYSpYadkgRmrWNl5g24JY": {"geometry": {"location": {"lat": 51.5373414, "lng": -0.1732809}, "viewport": {"northeast": {"lat": 51.5387177802915, "lng": -0.171875519708498}, "southwest": {"lat": 51.5360198197085, "lng": -0.174573480291502}}}, "name": "Rossetti House", "place_id": "ChIJ-2xYSpYadkgRmrWNl5g24JY", "types": ["point_of_interest", "establishment"], "rating": 5, "user_ratings_total": 2}, "ChIJMdoMT5cadkgR1JKIPuqb34s": {"geometry": {"location": {"lat": 51.54059505515741, "lng": -0.1755057280997417}, "viewport": {"northeast": {"lat": 51.5419412302915, "lng": -0.174132369708498}, "southwest": {"lat": 51.5392432697085, "lng": -0.176830330291502}}}, "name": "Finchley Road", "place_id": "ChIJMdoMT5cadkgR1JKIPuqb34s", "types": ["route"]}, "ChIJ4dUbOJcadkgRj19Kwlz7B-c": {"geometry": {"location": {"lat": 51.5404783, "lng": -0.1748924}, "viewport": {"northeast": {"lat": 51.54183198029149, "lng": -0.173620569708498}, "southwest": {"lat": 51.5391340197085, "lng": -0.176318530291502}}}, "name": "E P C International Ltd", "place_id": "ChIJ4dUbOJcadkgRj19Kwlz7B-c", "types": ["point_of_interest", "establishment"]}, "ChIJ0f0VW5cadkgR9xA_KEq-7_Q": {"geometry": {"location": {"lat": 51.5403051, "lng": -0.1757748}, "viewport": {"northeast": {"lat": 51.54165103029149, "lng": -0.174385819708498}, "southwest": {"lat": 51.53895306970849, "lng": -0.177083780291502}}}, "name": "Boundary Road Finchley Road (Stop B)", "place_id": "ChIJ0f0VW5cadkgR9xA_KEq-7_Q", "types": ["transit_station", "point_of_interest", "establishment"], "rating": 4, "user_ratings_total": 1}, "ChIJyZPmZ5cadkgRXb-k7LUPO-4": {"geometry": {"location": {"lat": 51.5397835, "lng": -0.175724}, "viewport": {"northeast": {"lat": 51.5411331302915, "lng": -0.174384019708498}, "southwest": {"lat": 51.5384351697085, "lng": -0.177081980291502}}}, "name": "Boundary Road Finchley Road", "place_id": "ChIJyZPmZ5cadkgRXb-k7LUPO-4", "types": ["transit_station", "point_of_interest", "establishment"]}, "ChIJNVELZZcadkgRDaJyh6J5fw0": {"geometry": {"location": {"lat": 51.53929910278384, "lng": -0.1757549342392456}, "viewport": {"northeast": {"lat": 51.5406542302915, "lng": -0.174433719708498}, "southwest": {"lat": 51.5379562697085, "lng": -0.177131680291502}}}, "name": "Finchley Road", "place_id": "ChIJNVELZZcadkgRDaJyh6J5fw0", "types": ["route"]}, "ChIJlQ6FEpcadkgR4-v0fPN8YCs": {"geometry": {"location": {"lat": 51.5392277, "lng": -0.1748056}, "viewport": {"northeast": {"lat": 51.5407343802915, "lng": -0.173424619708498}, "southwest": {"lat": 51.5380364197085, "lng": -0.176122580291502}}}, "name": "Jerusalem Ball", "place_id": "ChIJlQ6FEpcadkgR4-v0fPN8YCs", "types": ["point_of_interest", "establishment"]}, "ChIJ710hdJcadkgRFOJHknpM_l0": {"geometry": {"location": {"lat": 51.5387662, "lng": -0.1752973}, "viewport": {"northeast": {"lat": 51.5401115302915, "lng": -0.173898119708498}, "southwest": {"lat": 51.5374135697085, "lng": -0.176596080291502}}}, "name": "Julie Anne Christoph", "place_id": "ChIJ710hdJcadkgRFOJHknpM_l0", "types": ["point_of_interest", "establishment"]}, "ChIJxZhhZZcadkgRe--pzxVxFEI": {"geometry": {"location": {"lat": 51.53933300000001, "lng": -0.175663}, "viewport": {"northeast": {"lat": 51.5406843802915, "lng": -0.174347719708498}, "southwest": {"lat": 51.5379864197085, "lng": -0.177045680291502}}}, "name": "Boundary Road Finchley Road (Stop V)", "place_id": "ChIJxZhhZZcadkgRe--pzxVxFEI", "types": ["transit_station", "point_of_interest", "establishment"]}, "ChIJYwKnE5cadkgR2P_HTwAloqo": {"geometry": {"location": {"lat": 51.539411, "lng": -0.1747591}, "viewport": {"northeast": {"lat": 51.54082453029149, "lng": -0.173382719708498}, "southwest": {"lat": 51.5381265697085, "lng": -0.176080680291502}}}, "name": "Buttermere Court", "place_id": "ChIJYwKnE5cadkgR2P_HTwAloqo", "types": ["bus_station", "transit_station", "point_of_interest", "establishment"], "rating": 4.1, "user_ratings_total": 12}, "ChIJE9U7gpcadkgRuPVvsZpWbGQ": {"geometry": {"location": {"lat": 51.53842138484705, "lng": -0.175985577612796}, "viewport": {"northeast": {"lat": 51.5397704302915, "lng": -0.174637469708498}, "southwest": {"lat": 51.5370724697085, "lng": -0.177335430291502}}}, "name": "Finchley Road", "place_id": "ChIJE9U7gpcadkgRuPVvsZpWbGQ", "types": ["route"]}, "ChIJhwpfnZcadkgRippwuW8ShPg": {"geometry": {"location": {"lat": 51.5378394, "lng": -0.1755392}, "viewport": {"northeast": {"lat": 51.5392287302915, "lng": -0.174162869708498}, "southwest": {"lat": 51.5365307697085, "lng": -0.176860830291502}}}, "name": "Avesta Accounting", "place_id": "ChIJhwpfnZcadkgRippwuW8ShPg", "types": ["accounting", "finance", "point_of_interest", "establishment"]}, "ChIJq0XXHkobdkgRg5SpgxLhQEI": {"geometry": {"location": {"lat": 51.53823699999999, "lng": -0.1756141}, "viewport": {"northeast": {"lat": 51.5395779802915, "lng": -0.174158469708498}, "southwest": {"lat": 51.5368800197085, "lng": -0.176856430291502}}}, "name": "Residential", "place_id": "ChIJq0XXHkobdkgRg5SpgxLhQEI", "types": ["point_of_interest", "establishment"]}, "ChIJ2XpadZcadkgRSRNvuj_B-34": {"geometry": {"location": {"lat": 51.538287, "lng": -0.1752183}, "viewport": {"northeast": {"lat": 51.5396422302915, "lng": -0.173952969708498}, "southwest": {"lat": 51.5369442697085, "lng": -0.176650930291502}}}, "name": "T A Braithwaithe & Associates Insurance Brokers Ltd", "place_id": "ChIJ2XpadZcadkgRSRNvuj_B-34", "types": ["insurance_agency", "point_of_interest", "establishment"], "rating": 1, "user_ratings_total": 1}, "ChIJB-7s9JcadkgROMxuw4o0SNo": {"geometry": {"location": {"lat": 51.53711044751606, "lng": -0.1761464822813495}, "viewport": {"northeast": {"lat": 51.5384593302915, "lng": -0.174796169708498}, "southwest": {"lat": 51.5357613697085, "lng": -0.177494130291502}}}, "name": "34-26 A41", "place_id": "ChIJB-7s9JcadkgROMxuw4o0SNo", "types": ["route"]}, "ChIJN7hd6ZcadkgR1h1qeZMumm0": {"geometry": {"location": {"lat": 51.5372272, "lng": -0.1754092}, "viewport": {"northeast": {"lat": 51.53852328029149, "lng": -0.174077819708498}, "southwest": {"lat": 51.5358253197085, "lng": -0.176775780291502}}}, "name": "4 Quarters Property Finder, Relocation Service & Buyers Agent", "place_id": "ChIJN7hd6ZcadkgR1h1qeZMumm0", "types": ["finance", "real_estate_agency", "general_contractor", "point_of_interest", "establishment"]}, "ChIJK5FdhL4adkgRpzH_qQj4FpE": {"geometry": {"location": {"lat": 51.53696, "lng": -0.1753388}, "viewport": {"northeast": {"lat": 51.53824168029151, "lng": -0.173906269708498}, "southwest": {"lat": 51.53554371970851, "lng": -0.176604230291502}}}, "name": "Laurence Leigh Residential Ltd", "place_id": "ChIJK5FdhL4adkgRpzH_qQj4FpE", "types": ["point_of_interest", "establishment"], "rating": 4.9, "user_ratings_total": 43}, "ChIJUWN07pcadkgRE0USr75GI9A": {"geometry": {"location": {"lat": 51.536874, "lng": -0.17557}, "viewport": {"northeast": {"lat": 51.5381478302915, "lng": -0.174127769708498}, "southwest": {"lat": 51.5354498697085, "lng": -0.176825730291502}}}, "name": "Mapco Investments Ltd", "place_id": "ChIJUWN07pcadkgRE0USr75GI9A", "types": ["general_contractor", "point_of_interest", "establishment"]}, "ChIJqSmX8pcadkgRo-mlwlvc3Dk": {"geometry": {"location": {"lat": 51.53699200000001, "lng": -0.175767}, "viewport": {"northeast": {"lat": 51.5383545802915, "lng": -0.174615869708498}, "southwest": {"lat": 51.5356566197085, "lng": -0.177313830291502}}}, "name": "The Garuda Pilates Studio", "place_id": "ChIJqSmX8pcadkgRo-mlwlvc3Dk", "types": ["gym", "health", "point_of_interest", "establishment"], "rating": 5, "user_ratings_total": 26}, "ChIJ7ThCwpcadkgRH1ppC3vQ8vQ": {"geometry": {"location": {"lat": 51.53678530000001, "lng": -0.1748383000000001}, "viewport": {"northeast": {"lat": 51.5381969302915, "lng": -0.173568319708498}, "southwest": {"lat": 51.5354989697085, "lng": -0.176266280291502}}}, "name": "Diving And Safety Boat Hire Contractors", "place_id": "ChIJ7ThCwpcadkgRH1ppC3vQ8vQ", "types": ["point_of_interest", "establishment"]}, "ChIJ-S8PTZYadkgRnaIfx--3Z68": {"geometry": {"location": {"lat": 51.53689789999999, "lng": -0.1753368}, "viewport": {"northeast": {"lat": 51.5381994302915, "lng": -0.173928519708498}, "southwest": {"lat": 51.5355014697085, "lng": -0.176626480291502}}}, "name": "St John's Wood Practice", "place_id": "ChIJ-S8PTZYadkgRnaIfx--3Z68", "types": ["dentist", "health", "point_of_interest", "establishment"], "rating": 2.1, "user_ratings_total": 48}, "ChIJTRZgZr0adkgR4BeY7YvkQz4": {"geometry": {"location": {"lat": 51.536466, "lng": -0.175574}, "viewport": {"northeast": {"lat": 51.5378788302915, "lng": -0.174087369708498}, "southwest": {"lat": 51.5351808697085, "lng": -0.176785330291502}}}, "name": "St. Johns Wood Electricians", "place_id": "ChIJTRZgZr0adkgR4BeY7YvkQz4", "types": ["electrician", "point_of_interest", "establishment"], "rating": 5, "user_ratings_total": 3}, "ChIJUWN07pcadkgRwHt7Eie5FDU": {"geometry": {"location": {"lat": 51.53694840000001, "lng": -0.1753776}, "viewport": {"northeast": {"lat": 51.5382278802915, "lng": -0.173942319708498}, "southwest": {"lat": 51.5355299197085, "lng": -0.176640280291502}}}, "name": "Cidabridge Properties Ltd", "place_id": "ChIJUWN07pcadkgRwHt7Eie5FDU", "types": ["general_contractor", "point_of_interest", "establishment"]}, "ChIJUWN07pcadkgR2e92Zl6gVK4": {"geometry": {"location": {"lat": 51.5368521, "lng": -0.1754325}, "viewport": {"northeast": {"lat": 51.53815348029151, "lng": -0.174024419708498}, "southwest": {"lat": 51.53545551970851, "lng": -0.176722380291502}}}, "name": "London Tokyo Property Services Ltd", "place_id": "ChIJUWN07pcadkgR2e92Zl6gVK4", "types": ["real_estate_agency", "point_of_interest", "establishment"], "rating": 3.3, "user_ratings_total": 3}, "ChIJ8Y3U8ZcadkgRt-_mM-kYfMA": {"geometry": {"location": {"lat": 51.53682999999999, "lng": -0.1756516}, "viewport": {"northeast": {"lat": 51.5380749302915, "lng": -0.174264669708498}, "southwest": {"lat": 51.5353769697085, "lng": -0.176962630291502}}}, "name": "Queens Grove Court", "place_id": "ChIJ8Y3U8ZcadkgRt-_mM-kYfMA", "types": ["point_of_interest", "establishment"], "rating": 4.5, "user_ratings_total": 4}, "ChIJLxmkE8IbdkgRZfiu8pRnWjg": {"geometry": {"location": {"lat": 51.5369915, "lng": -0.1757671}, "viewport": {"northeast": {"lat": 51.5383540802915, "lng": -0.174615969708498}, "southwest": {"lat": 51.5356561197085, "lng": -0.177313930291502}}}, "name": "CAT LIKE MOVEMENT", "place_id": "ChIJLxmkE8IbdkgRZfiu8pRnWjg", "types": ["point_of_interest", "establishment"], "rating": 5, "user_ratings_total": 4}, "ChIJdVnvQ2cbdkgRaUebIhbnduA": {"geometry": {"location": {"lat": 51.53699200000001, "lng": -0.175767}, "viewport": {"northeast": {"lat": 51.5383545802915, "lng": -0.174615869708498}, "southwest": {"lat": 51.5356566197085, "lng": -0.177313830291502}}}, "name": "Thomas Hood Blue Plaque", "place_id": "ChIJdVnvQ2cbdkgRaUebIhbnduA", "types": ["point_of_interest", "establishment"], "rating": 4, "user_ratings_total": 1}, "ChIJNxkU7JcadkgRytP06iQM3PQ": {"geometry": {"location": {"lat": 51.5372076, "lng": -0.1754316}, "viewport": {"northeast": {"lat": 51.53851443029149, "lng": -0.174096669708498}, "southwest": {"lat": 51.53581646970849, "lng": -0.176794630291502}}}, "name": "4 Quarters Online Estate Agent", "place_id": "ChIJNxkU7JcadkgRytP06iQM3PQ", "types": ["real_estate_agency", "finance", "point_of_interest", "establishment"]}, "ChIJYyC68pcadkgRMB13SPRo1Sw": {"geometry": {"location": {"lat": 51.5371231, "lng": -0.1757338}, "viewport": {"northeast": {"lat": 51.53848603029149, "lng": -0.174587569708498}, "southwest": {"lat": 51.5357880697085, "lng": -0.177285530291502}}}, "name": "Patel M M & Co", "place_id": "ChIJYyC68pcadkgRMB13SPRo1Sw", "types": ["lawyer", "point_of_interest", "establishment"]}, "ChIJ2zKIYdMbdkgRfgIGqFCf9L8": {"geometry": {"location": {"lat": 51.5371363, "lng": -0.1757396}, "viewport": {"northeast": {"lat": 51.5385006802915, "lng": -0.174588969708498}, "southwest": {"lat": 51.5358027197085, "lng": -0.177286930291502}}}, "name": "Entreprise & D\u00e9cisions - Londres", "place_id": "ChIJ2zKIYdMbdkgRfgIGqFCf9L8", "types": ["finance", "point_of_interest", "establishment"]}, "ChIJ0xbI8pcadkgRZW6gEtpsKUA": {"geometry": {"location": {"lat": 51.5371829, "lng": -0.1757727}, "viewport": {"northeast": {"lat": 51.5385456802915, "lng": -0.174601169708498}, "southwest": {"lat": 51.5358477197085, "lng": -0.177299130291502}}}, "name": "Mayfair Property Services", "place_id": "ChIJ0xbI8pcadkgRZW6gEtpsKUA", "types": ["real_estate_agency", "point_of_interest", "establishment"]}, "ChIJ_cqX9pcadkgRbt6qEcCXfaU": {"geometry": {"location": {"lat": 51.536785, "lng": -0.176111}, "viewport": {"northeast": {"lat": 51.5381222302915, "lng": -0.174804669708498}, "southwest": {"lat": 51.5354242697085, "lng": -0.177502630291502}}}, "name": "Queen's Grove (Stop U)", "place_id": "ChIJ_cqX9pcadkgRbt6qEcCXfaU", "types": ["transit_station", "point_of_interest", "establishment"], "rating": 3.5, "user_ratings_total": 2}, "ChIJD7chVr0adkgRSSEcDzW8E_k": {"geometry": {"location": {"lat": 51.53600849999999, "lng": -0.1755544}, "viewport": {"northeast": {"lat": 51.53730748029149, "lng": -0.174391619708498}, "southwest": {"lat": 51.5346095197085, "lng": -0.177089580291502}}}, "name": "Marcus Cooper Group", "place_id": "ChIJD7chVr0adkgRSSEcDzW8E_k", "types": ["general_contractor", "point_of_interest", "establishment"], "rating": 3.1, "user_ratings_total": 42}, "ChIJSd8y_ZcadkgRwdQnWNL_6us": {"geometry": {"location": {"lat": 51.5360189, "lng": -0.175674}, "viewport": {"northeast": {"lat": 51.53733408029151, "lng": -0.174465619708498}, "southwest": {"lat": 51.53463611970851, "lng": -0.177163580291502}}}, "name": "Abbey Professional Builders", "place_id": "ChIJSd8y_ZcadkgRwdQnWNL_6us", "types": ["general_contractor", "point_of_interest", "establishment"]}, "ChIJIbchVr0adkgR4WujSdz5Ewg": {"geometry": {"location": {"lat": 51.53589299999999, "lng": -0.175938}, "viewport": {"northeast": {"lat": 51.5372344802915, "lng": -0.174617019708498}, "southwest": {"lat": 51.5345365197085, "lng": -0.177314980291502}}}, "name": "Solomons Solicitors", "place_id": "ChIJIbchVr0adkgR4WujSdz5Ewg", "types": ["point_of_interest", "establishment"], "rating": 5, "user_ratings_total": 3}, "ChIJ57LIkXD-dUgRhPGS8_zPvuM": {"geometry": {"location": {"lat": 51.53606869999999, "lng": -0.1758278}, "viewport": {"northeast": {"lat": 51.53739823029149, "lng": -0.174565869708498}, "southwest": {"lat": 51.53470026970849, "lng": -0.177263830291502}}}, "name": "HSS Hire", "place_id": "ChIJ57LIkXD-dUgRhPGS8_zPvuM", "types": ["point_of_interest", "establishment"], "rating": 3.4, "user_ratings_total": 9}, "ChIJM7pI_pcadkgRCMTF4dZGWrU": {"geometry": {"location": {"lat": 51.5360044, "lng": -0.1761798}, "viewport": {"northeast": {"lat": 51.5373565302915, "lng": -0.174820669708498}, "southwest": {"lat": 51.5346585697085, "lng": -0.177518630291502}}}, "name": "C a Hart", "place_id": "ChIJM7pI_pcadkgRCMTF4dZGWrU", "types": ["car_repair", "point_of_interest", "establishment"]}, "ChIJcTCRZ74bdkgRw12iD5EN9u4": {"geometry": {"location": {"lat": 51.53600849999999, "lng": -0.1755544}, "viewport": {"northeast": {"lat": 51.53730748029149, "lng": -0.174391619708498}, "southwest": {"lat": 51.5346095197085, "lng": -0.177089580291502}}}, "name": "Skips Noble St John's Wood", "place_id": "ChIJcTCRZ74bdkgRw12iD5EN9u4", "types": ["point_of_interest", "establishment"]}, "ChIJg--w9acbdkgRj47eMRSJDjs": {"geometry": {"location": {"lat": 51.53606869999999, "lng": -0.1758278}, "viewport": {"northeast": {"lat": 51.53739823029149, "lng": -0.174565869708498}, "southwest": {"lat": 51.53470026970849, "lng": -0.177263830291502}}}, "name": "The Freehold Partnership", "place_id": "ChIJg--w9acbdkgRj47eMRSJDjs", "types": ["finance", "point_of_interest", "establishment"]}, "ChIJzQdU8igbdkgRM9WJ1nNYZSA": {"geometry": {"location": {"lat": 51.53606869999999, "lng": -0.1758278}, "viewport": {"northeast": {"lat": 51.53739823029149, "lng": -0.174565869708498}, "southwest": {"lat": 51.53470026970849, "lng": -0.177263830291502}}}, "name": "Red Cannon Developments", "place_id": "ChIJzQdU8igbdkgRM9WJ1nNYZSA", "types": ["finance", "point_of_interest", "establishment"]}, "ChIJuwgC_ZcadkgRjdWDUN7Z9JQ": {"geometry": {"location": {"lat": 51.53606869999999, "lng": -0.1758278}, "viewport": {"northeast": {"lat": 51.53739823029149, "lng": -0.174565869708498}, "southwest": {"lat": 51.53470026970849, "lng": -0.177263830291502}}}, "name": "X Trim Fitness", "place_id": "ChIJuwgC_ZcadkgRjdWDUN7Z9JQ", "types": ["gym", "health", "point_of_interest", "establishment"]}, "ChIJuwgC_ZcadkgR0XPxPQXywr8": {"geometry": {"location": {"lat": 51.53606869999999, "lng": -0.1758278}, "viewport": {"northeast": {"lat": 51.53739823029149, "lng": -0.174565869708498}, "southwest": {"lat": 51.53470026970849, "lng": -0.177263830291502}}}, "name": "Oakley Projects UK Ltd", "place_id": "ChIJuwgC_ZcadkgR0XPxPQXywr8", "types": ["point_of_interest", "establishment"]}, "ChIJKbdI_pcadkgReoskJXanIyg": {"geometry": {"location": {"lat": 51.5362138, "lng": -0.1756478}, "viewport": {"northeast": {"lat": 51.5375272302915, "lng": -0.174503569708498}, "southwest": {"lat": 51.5348292697085, "lng": -0.177201530291502}}}, "name": "MiNK London", "place_id": "ChIJKbdI_pcadkgReoskJXanIyg", "types": ["point_of_interest", "establishment"]}, "ChIJ1ei4wZkadkgRimJrsxeRnxw": {"geometry": {"location": {"lat": 51.53975210056637, "lng": -0.177589949778613}, "viewport": {"northeast": {"lat": 51.5411010802915, "lng": -0.176240969708498}, "southwest": {"lat": 51.5384031197085, "lng": -0.178938930291502}}}, "name": "7-9 Boundary Rd", "place_id": "ChIJ1ei4wZkadkgRimJrsxeRnxw", "types": ["route"]}, "ChIJM5tn4pkadkgRYWx9l0LPoKU": {"geometry": {"location": {"lat": 51.5403598, "lng": -0.1766807}, "viewport": {"northeast": {"lat": 51.5417030802915, "lng": -0.175249519708498}, "southwest": {"lat": 51.5390051197085, "lng": -0.177947480291502}}}, "name": "Goni Glass", "place_id": "ChIJM5tn4pkadkgRYWx9l0LPoKU", "types": ["point_of_interest", "establishment"], "rating": 5, "user_ratings_total": 4}, "ChIJ1xtggO0adkgR5qx2XGBMXpk": {"geometry": {"location": {"lat": 51.54029910000001, "lng": -0.1771234}, "viewport": {"northeast": {"lat": 51.54162763029151, "lng": -0.175478919708498}, "southwest": {"lat": 51.53892966970851, "lng": -0.1781768802915021}}}, "name": "Belsize Osteopathic Practice", "place_id": "ChIJ1xtggO0adkgR5qx2XGBMXpk", "types": ["health", "point_of_interest", "establishment"], "rating": 5, "user_ratings_total": 11}, "ChIJM6_F5JkadkgRIrZm80Yjwpo": {"geometry": {"location": {"lat": 51.54045559999999, "lng": -0.1769273}, "viewport": {"northeast": {"lat": 51.5417898802915, "lng": -0.175365819708498}, "southwest": {"lat": 51.5390919197085, "lng": -0.178063780291502}}}, "name": "Vivid Universe", "place_id": "ChIJM6_F5JkadkgRIrZm80Yjwpo", "types": ["art_gallery", "point_of_interest", "establishment"]}, "ChIJA7lp45kadkgRBk1CMs1-Umo": {"geometry": {"location": {"lat": 51.5404171, "lng": -0.1767407}, "viewport": {"northeast": {"lat": 51.54175798029149, "lng": -0.1752748197084979}, "southwest": {"lat": 51.53906001970849, "lng": -0.177972780291502}}}, "name": "dmmartialart", "place_id": "ChIJA7lp45kadkgRBk1CMs1-Umo", "types": ["health", "point_of_interest", "establishment"], "rating": 5, "user_ratings_total": 1}, "ChIJHQea4pkadkgRoLZNpVCNdXE": {"geometry": {"location": {"lat": 51.540401, "lng": -0.176479}, "viewport": {"northeast": {"lat": 51.54174838029149, "lng": -0.175107219708498}, "southwest": {"lat": 51.5390504197085, "lng": -0.177805180291502}}}, "name": "REBT Ltd.", "place_id": "ChIJHQea4pkadkgRoLZNpVCNdXE", "types": ["point_of_interest", "establishment"]}, "ChIJ19tcM5gadkgRlUIJx0K7A7E": {"geometry": {"location": {"lat": 51.53896277722254, "lng": -0.177382362789353}, "viewport": {"northeast": {"lat": 51.5403114802915, "lng": -0.176030069708498}, "southwest": {"lat": 51.5376135197085, "lng": -0.178728030291502}}}, "name": "47-55 Marlborough Hill", "place_id": "ChIJ19tcM5gadkgRlUIJx0K7A7E", "types": ["route"]}, "ChIJcdQsypkadkgReFSy_G4yYUw": {"geometry": {"location": {"lat": 51.5388307, "lng": -0.1777134}, "viewport": {"northeast": {"lat": 51.5401685302915, "lng": -0.176216219708498}, "southwest": {"lat": 51.53747056970851, "lng": -0.1789141802915021}}}, "name": "Citi Alliance", "place_id": "ChIJcdQsypkadkgReFSy_G4yYUw", "types": ["finance", "point_of_interest", "establishment"]}, "ChIJfdFWxZkadkgRvUGw9sN56ho": {"geometry": {"location": {"lat": 51.53920900000001, "lng": -0.177195}, "viewport": {"northeast": {"lat": 51.5405878802915, "lng": -0.175832919708498}, "southwest": {"lat": 51.5378899197085, "lng": -0.178530880291502}}}, "name": "ubitricity Charging Station", "place_id": "ChIJfdFWxZkadkgRvUGw9sN56ho", "types": ["point_of_interest", "establishment"]}, "ChIJl0vHzpkadkgRCp84gqsPj6U": {"geometry": {"location": {"lat": 51.538947, "lng": -0.177461}, "viewport": {"northeast": {"lat": 51.5402937802915, "lng": -0.176088819708498}, "southwest": {"lat": 51.5375958197085, "lng": -0.178786780291502}}}, "name": "ubitricity Charging Station", "place_id": "ChIJl0vHzpkadkgRCp84gqsPj6U", "types": ["point_of_interest", "establishment"]}, "ChIJQ8boJJgadkgRba2RxWISBHI": {"geometry": {"location": {"lat": 51.5389507, "lng": -0.1766941}, "viewport": {"northeast": {"lat": 51.54031593029149, "lng": -0.175570119708498}, "southwest": {"lat": 51.53761796970849, "lng": -0.178268080291502}}}, "name": "Harris Academy St John's Wood", "place_id": "ChIJQ8boJJgadkgRba2RxWISBHI", "types": ["point_of_interest", "establishment"], "rating": 2.8, "user_ratings_total": 103}, "ChIJJZSU-sEbdkgRh-9TGzhk-Ug": {"geometry": {"location": {"lat": 51.53914809999999, "lng": -0.1775764}, "viewport": {"northeast": {"lat": 51.54048633029149, "lng": -0.176110869708498}, "southwest": {"lat": 51.53778836970849, "lng": -0.178808830291502}}}, "name": "Daily Tiffin Club", "place_id": "ChIJJZSU-sEbdkgRh-9TGzhk-Ug", "types": ["food", "point_of_interest", "establishment"]}, "ChIJ19tcM5gadkgR4OhDw6xzwI8": {"geometry": {"location": {"lat": 51.53820555343221, "lng": -0.1775338090871477}, "viewport": {"northeast": {"lat": 51.53955463029151, "lng": -0.176186069708498}, "southwest": {"lat": 51.53685666970851, "lng": -0.178884030291502}}}, "name": "70 Marlborough Hill", "place_id": "ChIJ19tcM5gadkgR4OhDw6xzwI8", "types": ["route"]}, "ChIJLSXHypkadkgRKokWboDBdHQ": {"geometry": {"location": {"lat": 51.5383429, "lng": -0.1777097}, "viewport": {"northeast": {"lat": 51.5396843802915, "lng": -0.176260919708498}, "southwest": {"lat": 51.5369864197085, "lng": -0.178958880291502}}}, "name": "Feng Shui Consultant", "place_id": "ChIJLSXHypkadkgRKokWboDBdHQ", "types": ["general_contractor", "point_of_interest", "establishment"]}, "ChIJy_PtMpgadkgRsDAl7wrNVq0": {"geometry": {"location": {"lat": 51.5384038, "lng": -0.1770917}, "viewport": {"northeast": {"lat": 51.5397676802915, "lng": -0.175941669708498}, "southwest": {"lat": 51.5370697197085, "lng": -0.178639630291502}}}, "name": "Bright Horizons St John's Wood Day Nursery and Preschool", "place_id": "ChIJy_PtMpgadkgRsDAl7wrNVq0", "types": ["school", "point_of_interest", "establishment"], "rating": 3.3, "user_ratings_total": 9}, "ChIJIXtnMZgadkgRL5axeuwM54E": {"geometry": {"location": {"lat": 51.538175, "lng": -0.17743}, "viewport": {"northeast": {"lat": 51.53952803029151, "lng": -0.176135119708498}, "southwest": {"lat": 51.53683006970851, "lng": -0.178833080291502}}}, "name": "ubitricity Charging Station", "place_id": "ChIJIXtnMZgadkgRL5axeuwM54E", "types": ["point_of_interest", "establishment"]}, "ChIJX8z-hE8bdkgRX4hcIiJ-fLk": {"geometry": {"location": {"lat": 51.5380115, "lng": -0.1777606}, "viewport": {"northeast": {"lat": 51.5393534802915, "lng": -0.176318369708498}, "southwest": {"lat": 51.5366555197085, "lng": -0.179016330291502}}}, "name": "Sir Bernard Spilsbury (1877-1947)", "place_id": "ChIJX8z-hE8bdkgRX4hcIiJ-fLk", "types": ["point_of_interest", "establishment"], "rating": 4, "user_ratings_total": 1}, "ChIJndbtPZgadkgRxVIRhGxSx1I": {"geometry": {"location": {"lat": 51.5372997, "lng": -0.1774266}, "viewport": {"northeast": {"lat": 51.53861650823551, "lng": -0.176099472652254}, "southwest": {"lat": 51.53591854765251, "lng": -0.178797433235258}}}, "name": "Parking lot", "place_id": "ChIJndbtPZgadkgRxVIRhGxSx1I", "types": ["parking", "premise", "point_of_interest", "establishment"]}, "ChIJVSgW-JcadkgRC_VwAMU1Fgo": {"geometry": {"location": {"lat": 51.53656466294737, "lng": -0.1763230556850048}, "viewport": {"northeast": {"lat": 51.53791383029149, "lng": -0.174968019708498}, "southwest": {"lat": 51.53521586970849, "lng": -0.177665980291502}}}, "name": "35 A41", "place_id": "ChIJVSgW-JcadkgRC_VwAMU1Fgo", "types": ["route"]}, "ChIJ35SSMpgadkgRNRaYX4ind84": {"geometry": {"location": {"lat": 51.5364534, "lng": -0.176922}, "viewport": {"northeast": {"lat": 51.5377925802915, "lng": -0.175269419708498}, "southwest": {"lat": 51.5350946197085, "lng": -0.177967380291502}}}, "name": "George Eliot Primary School", "place_id": "ChIJ35SSMpgadkgRNRaYX4ind84", "types": ["primary_school", "school", "point_of_interest", "establishment"], "rating": 4.4, "user_ratings_total": 15}, "ChIJd6sC9pcadkgRvfLJZGlFtqs": {"geometry": {"location": {"lat": 51.536854, "lng": -0.176425}, "viewport": {"northeast": {"lat": 51.53820238029149, "lng": -0.175024969708498}, "southwest": {"lat": 51.5355044197085, "lng": -0.177722930291502}}}, "name": "Queen's Grove (Stop A)", "place_id": "ChIJd6sC9pcadkgRvfLJZGlFtqs", "types": ["transit_station", "point_of_interest", "establishment"], "rating": 4, "user_ratings_total": 1}, "ChIJy-RDFZgadkgRuiH26LXY9g4": {"geometry": {"location": {"lat": 51.537157, "lng": -0.177814}, "viewport": {"northeast": {"lat": 51.53850483029149, "lng": -0.176445119708498}, "southwest": {"lat": 51.5358068697085, "lng": -0.179143080291502}}}, "name": "ubitricity Charging Station", "place_id": "ChIJy-RDFZgadkgRuiH26LXY9g4", "types": ["point_of_interest", "establishment"]}, "ChIJk9peFZgadkgR76c_ZNR8eog": {"geometry": {"location": {"lat": 51.5372046, "lng": -0.177814}, "viewport": {"northeast": {"lat": 51.5385519802915, "lng": -0.176438019708498}, "southwest": {"lat": 51.5358540197085, "lng": -0.179135980291502}}}, "name": "Zipcar", "place_id": "ChIJk9peFZgadkgR76c_ZNR8eog", "types": ["car_rental", "point_of_interest", "establishment"], "rating": 5, "user_ratings_total": 2}, "ChIJccVv9pcadkgR5tQx5aCyNBE": {"geometry": {"location": {"lat": 51.5368465, "lng": -0.1762815}, "viewport": {"northeast": {"lat": 51.53819538029149, "lng": -0.174923469708498}, "southwest": {"lat": 51.5354974197085, "lng": -0.177621430291502}}}, "name": "Queen's Grove", "place_id": "ChIJccVv9pcadkgR5tQx5aCyNBE", "types": ["transit_station", "point_of_interest", "establishment"]}, "ChIJ_7e0kJkadkgRcRAmdkZmAZw": {"geometry": {"location": {"lat": 51.54017717405524, "lng": -0.1785632157693324}, "viewport": {"northeast": {"lat": 51.5415251802915, "lng": -0.177217969708498}, "southwest": {"lat": 51.5388272197085, "lng": -0.179915930291502}}}, "name": "47-51 Loudoun Rd", "place_id": "ChIJ_7e0kJkadkgRcRAmdkZmAZw", "types": ["route"]}, "ChIJy40F4bobdkgRT1LApU64mzs": {"geometry": {"location": {"lat": 51.5400262, "lng": -0.1781527}, "viewport": {"northeast": {"lat": 51.5413310302915, "lng": -0.176807969708498}, "southwest": {"lat": 51.5386330697085, "lng": -0.179505930291502}}}, "name": "CakeFace Makeup", "place_id": "ChIJy40F4bobdkgRT1LApU64mzs", "types": ["point_of_interest", "establishment"], "rating": 5, "user_ratings_total": 2}, "ChIJSecalpkadkgRlC9Ze-ItWjE": {"geometry": {"location": {"lat": 51.54017450000001, "lng": -0.1781171}, "viewport": {"northeast": {"lat": 51.5414782802915, "lng": -0.176957319708498}, "southwest": {"lat": 51.5387803197085, "lng": -0.179655280291502}}}, "name": "Geetas Food", "place_id": "ChIJSecalpkadkgRlC9Ze-ItWjE", "types": ["food", "point_of_interest", "establishment"], "rating": 1, "user_ratings_total": 1}, "ChIJ_2E2g5kadkgR-GZ9mC889dY": {"geometry": {"location": {"lat": 51.5404299, "lng": -0.1789611}, "viewport": {"northeast": {"lat": 51.5418039802915, "lng": -0.177524969708498}, "southwest": {"lat": 51.5391060197085, "lng": -0.180222930291502}}}, "name": "Templar Financial Planning Ltd", "place_id": "ChIJ_2E2g5kadkgR-GZ9mC889dY", "types": ["finance", "point_of_interest", "establishment"], "rating": 1, "user_ratings_total": 1}, "ChIJSecalpkadkgRrEs8BrxPf2A": {"geometry": {"location": {"lat": 51.54010450000001, "lng": -0.1781129}, "viewport": {"northeast": {"lat": 51.5414123802915, "lng": -0.176936119708498}, "southwest": {"lat": 51.5387144197085, "lng": -0.179634080291502}}}, "name": "S B T J Africa", "place_id": "ChIJSecalpkadkgRrEs8BrxPf2A", "types": ["point_of_interest", "establishment"], "rating": 1, "user_ratings_total": 1}, "ChIJ1xoYspkadkgRAEuXL0wCF58": {"geometry": {"location": {"lat": 51.53881380002488, "lng": -0.1785213006473082}, "viewport": {"northeast": {"lat": 51.5401627802915, "lng": -0.177172319708498}, "southwest": {"lat": 51.5374648197085, "lng": -0.179870280291502}}}, "name": "33 Loudoun Rd", "place_id": "ChIJ1xoYspkadkgRAEuXL0wCF58", "types": ["route"]}, "ChIJ2x-6r5kadkgRU7tgz0a08Fc": {"geometry": {"location": {"lat": 51.5390689, "lng": -0.1787498}, "viewport": {"northeast": {"lat": 51.5404154302915, "lng": -0.177398819708498}, "southwest": {"lat": 51.5377174697085, "lng": -0.180096780291502}}}, "name": "Zipcar", "place_id": "ChIJ2x-6r5kadkgRU7tgz0a08Fc", "types": ["car_rental", "point_of_interest", "establishment"], "rating": 3, "user_ratings_total": 1}, "ChIJjw11upkadkgRbuyTJcpfpaM": {"geometry": {"location": {"lat": 51.539194, "lng": -0.178368}, "viewport": {"northeast": {"lat": 51.54054483029149, "lng": -0.177045419708498}, "southwest": {"lat": 51.5378468697085, "lng": -0.179743380291502}}}, "name": "ubitricity Charging Station", "place_id": "ChIJjw11upkadkgRbuyTJcpfpaM", "types": ["point_of_interest", "establishment"]}, "ChIJFxBirZkadkgRSqXhTouc-hA": {"geometry": {"location": {"lat": 51.5386359, "lng": -0.1786349}, "viewport": {"northeast": {"lat": 51.5399828302915, "lng": -0.177259069708498}, "southwest": {"lat": 51.5372848697085, "lng": -0.179957030291502}}}, "name": "ubitricity Charging Station", "place_id": "ChIJFxBirZkadkgRSqXhTouc-hA", "types": ["point_of_interest", "establishment"]}, "ChIJrez3UZgadkgRcWQkug9kms8": {"geometry": {"location": {"lat": 51.53817840001091, "lng": -0.1786484502785522}, "viewport": {"northeast": {"lat": 51.5395273802915, "lng": -0.177299469708498}, "southwest": {"lat": 51.5368294197085, "lng": -0.1799974302915021}}}, "name": "29-31 Loudoun Rd", "place_id": "ChIJrez3UZgadkgRcWQkug9kms8", "types": ["route"]}, "ChIJM9-tXpgadkgR9b-BjZYkpKk": {"geometry": {"location": {"lat": 51.5374622, "lng": -0.1790308}, "viewport": {"northeast": {"lat": 51.5388016802915, "lng": -0.177565469708498}, "southwest": {"lat": 51.5361037197085, "lng": -0.180263430291502}}}, "name": "Brasserie Cafe Med", "place_id": "ChIJM9-tXpgadkgR9b-BjZYkpKk", "types": ["restaurant", "food", "point_of_interest", "establishment"], "rating": 4.1, "user_ratings_total": 165}, "ChIJ_x0jZJgadkgRfTzKQwtSqZY": {"geometry": {"location": {"lat": 51.53684820435365, "lng": -0.1789052182833256}, "viewport": {"northeast": {"lat": 51.5381964302915, "lng": -0.177507869708498}, "southwest": {"lat": 51.5354984697085, "lng": -0.180205830291502}}}, "name": "82-26 Loudoun Rd", "place_id": "ChIJ_x0jZJgadkgRfTzKQwtSqZY", "types": ["route"]}, "ChIJy7HTZpgadkgR6BmMbED8g9Y": {"geometry": {"location": {"lat": 51.53702200000001, "lng": -0.178975}, "viewport": {"northeast": {"lat": 51.5383686802915, "lng": -0.177585819708498}, "southwest": {"lat": 51.5356707197085, "lng": -0.180283780291502}}}, "name": "ubitricity Charging Station", "place_id": "ChIJy7HTZpgadkgR6BmMbED8g9Y", "types": ["point_of_interest", "establishment"]}, "ChIJhZVZe5gadkgR_cjxnX40TtE": {"geometry": {"location": {"lat": 51.536511, "lng": -0.178969}, "viewport": {"northeast": {"lat": 51.5378613802915, "lng": -0.1775820197084979}, "southwest": {"lat": 51.5351634197085, "lng": -0.180279980291502}}}, "name": "ubitricity Charging Station", "place_id": "ChIJhZVZe5gadkgR_cjxnX40TtE", "types": ["point_of_interest", "establishment"]}, "ChIJZYuIfQYbdkgRbiZwuuKCgyw": {"geometry": {"location": {"lat": 51.5367397, "lng": -0.1781281}, "viewport": {"northeast": {"lat": 51.5380908302915, "lng": -0.176612869708498}, "southwest": {"lat": 51.5353928697085, "lng": -0.179310830291502}}}, "name": "YinghaoAcu Ltd", "place_id": "ChIJZYuIfQYbdkgRbiZwuuKCgyw", "types": ["health", "point_of_interest", "establishment"]}, "ChIJYcpqeZgadkgR7XvoFvcb7_I": {"geometry": {"location": {"lat": 51.536148, "lng": -0.178886}, "viewport": {"northeast": {"lat": 51.53750158029149, "lng": -0.177497119708498}, "southwest": {"lat": 51.5348036197085, "lng": -0.180195080291502}}}, "name": "ubitricity Charging Station", "place_id": "ChIJYcpqeZgadkgR7XvoFvcb7_I", "types": ["point_of_interest", "establishment"]}, "ChIJkThk4pYadkgRLTprYffDRJk": {"geometry": {"location": {"lat": 51.53946376828913, "lng": -0.1731996763432316}, "viewport": {"northeast": {"lat": 51.54077048029149, "lng": -0.172062819708498}, "southwest": {"lat": 51.5380725197085, "lng": -0.174760780291502}}}, "name": "2-8 Queensmead", "place_id": "ChIJkThk4pYadkgRLTprYffDRJk", "types": ["route"]}, "ChIJbQWlS5YadkgRt1EvgmPpiRQ": {"geometry": {"location": {"lat": 51.53746390022719, "lng": -0.1732530990648166}, "viewport": {"northeast": {"lat": 51.5388128802915, "lng": -0.171904119708498}, "southwest": {"lat": 51.5361149197085, "lng": -0.174602080291502}}}, "name": "48-44 Ordnance Hill", "place_id": "ChIJbQWlS5YadkgRt1EvgmPpiRQ", "types": ["route"]}, "ChIJtz0LFJcadkgRAyD2REs_qqo": {"geometry": {"location": {"lat": 51.53952662229221, "lng": -0.1745321228674463}, "viewport": {"northeast": {"lat": 51.5408738802915, "lng": -0.173183619708498}, "southwest": {"lat": 51.5381759197085, "lng": -0.175881580291502}}}, "name": "2 Boundary Rd", "place_id": "ChIJtz0LFJcadkgRAyD2REs_qqo", "types": ["route"]}, "ChIJRUk6qJcadkgR2vBlhq1FYtM": {"geometry": {"location": {"lat": 51.53848884079244, "lng": -0.1740901863393637}, "viewport": {"northeast": {"lat": 51.53983753029149, "lng": -0.172727069708498}, "southwest": {"lat": 51.53713956970849, "lng": -0.175425030291502}}}, "name": "22-28 St John's Wood Park", "place_id": "ChIJRUk6qJcadkgR2vBlhq1FYtM", "types": ["route"]}, "ChIJ8fxN55cadkgRYSDcHznsH6E": {"geometry": {"location": {"lat": 51.53604681663273, "lng": -0.174669789531001}, "viewport": {"northeast": {"lat": 51.5373861802915, "lng": -0.173373469708498}, "southwest": {"lat": 51.5346882197085, "lng": -0.176071430291502}}}, "name": "2-7 Queen's Terrace", "place_id": "ChIJ8fxN55cadkgRYSDcHznsH6E", "types": ["route"]}, "ChIJm3LWRJcadkgRXt_WgzNJ4Ak": {"geometry": {"location": {"lat": 51.5403741301059, "lng": -0.1756698220540383}, "viewport": {"northeast": {"lat": 51.54187220000004, "lng": -0.1743074697084979}, "southwest": {"lat": 51.53887299999995, "lng": -0.177005430291502}}}, "name": "53-79 A41", "place_id": "ChIJm3LWRJcadkgRXt_WgzNJ4Ak", "types": ["route"]}, "ChIJ1YaTrQ0bdkgRVhiK25_Zbzo": {"geometry": {"location": {"lat": 51.5406369, "lng": -0.175931}, "viewport": {"northeast": {"lat": 51.5419744302915, "lng": -0.174428219708498}, "southwest": {"lat": 51.5392764697085, "lng": -0.177126180291502}}}, "name": "The Nest", "place_id": "ChIJ1YaTrQ0bdkgRVhiK25_Zbzo", "types": ["meal_takeaway", "restaurant", "food", "point_of_interest", "establishment"]}, "ChIJSzDlUJcadkgR4dfYDCv4d64": {"geometry": {"location": {"lat": 51.5406369, "lng": -0.175931}, "viewport": {"northeast": {"lat": 51.5419726302915, "lng": -0.174427769708498}, "southwest": {"lat": 51.5392746697085, "lng": -0.177125730291502}}}, "name": "'The Pursuit of Ideas', Leon Underwood", "place_id": "ChIJSzDlUJcadkgR4dfYDCv4d64", "types": ["point_of_interest", "establishment"]}, "ChIJcWsBZZcadkgRtV4qJjQZT5w": {"geometry": {"location": {"lat": 51.53930838123131, "lng": -0.1758786873666902}, "viewport": {"northeast": {"lat": 51.5406577802915, "lng": -0.174515369708498}, "southwest": {"lat": 51.5379598197085, "lng": -0.177213330291502}}}, "name": "37-51 A41", "place_id": "ChIJcWsBZZcadkgRtV4qJjQZT5w", "types": ["route"]}, "ChIJ1zdzdOEbdkgRtkWWcoCiCi0": {"geometry": {"location": {"lat": 51.5397262, "lng": -0.1764639}, "viewport": {"northeast": {"lat": 51.5410502802915, "lng": -0.175119569708498}, "southwest": {"lat": 51.5383523197085, "lng": -0.177817530291502}}}, "name": "Zipcar", "place_id": "ChIJ1zdzdOEbdkgRtkWWcoCiCi0", "types": ["point_of_interest", "establishment"]}, "ChIJE0wB9ZcadkgR0xJzliGcu2w": {"geometry": {"location": {"lat": 51.53714257778802, "lng": -0.1762996066441037}, "viewport": {"northeast": {"lat": 51.5384811302915, "lng": -0.174892969708498}, "southwest": {"lat": 51.5357831697085, "lng": -0.177590930291502}}}, "name": "Finchley Road", "place_id": "ChIJE0wB9ZcadkgR0xJzliGcu2w", "types": ["route"]}, "ChIJYfjC-JcadkgRAZpAXjsSZFo": {"geometry": {"location": {"lat": 51.5363063567626, "lng": -0.1762835026684312}, "viewport": {"northeast": {"lat": 51.53765568029149, "lng": -0.174931269708498}, "southwest": {"lat": 51.5349577197085, "lng": -0.177629230291502}}}, "name": "Finchley Road", "place_id": "ChIJYfjC-JcadkgRAZpAXjsSZFo", "types": ["route"]}, "ChIJZaRQ_pcadkgRZ9Bx4n-zAFY": {"geometry": {"location": {"lat": 51.53604499999999, "lng": -0.176178}, "viewport": {"northeast": {"lat": 51.5373875802915, "lng": -0.174847769708498}, "southwest": {"lat": 51.5346896197085, "lng": -0.177545730291502}}}, "name": "Java Tutor", "place_id": "ChIJZaRQ_pcadkgRZ9Bx4n-zAFY", "types": ["university", "point_of_interest", "establishment"], "rating": 5, "user_ratings_total": 2}, "ChIJXenSBX8QdkgR0LYsq3s-7KA": {"geometry": {"location": {"lat": 51.5364294, "lng": -0.1764839}, "viewport": {"northeast": {"lat": 51.5377000802915, "lng": -0.1750302697084979}, "southwest": {"lat": 51.5350021197085, "lng": -0.177728230291502}}}, "name": "TBAP Beachcroft AP Academy", "place_id": "ChIJXenSBX8QdkgR0LYsq3s-7KA", "types": ["school", "point_of_interest", "establishment"], "rating": 3.5, "user_ratings_total": 4}, "ChIJo1mv6z4xcEERIJ-XP00C26c": {"geometry": {"location": {"lat": 51.5406486, "lng": -0.1783283}, "viewport": {"northeast": {"lat": 51.5420664802915, "lng": -0.176984819708498}, "southwest": {"lat": 51.5393685197085, "lng": -0.179682780291502}}}, "name": "Ready Steady Go", "place_id": "ChIJo1mv6z4xcEERIJ-XP00C26c", "types": ["school", "point_of_interest", "establishment"], "rating": 5, "user_ratings_total": 1}, "ChIJC6C-jZkadkgRb-IPHEhyubw": {"geometry": {"location": {"lat": 51.54060079999999, "lng": -0.1781611}, "viewport": {"northeast": {"lat": 51.54204513029149, "lng": -0.1768190197084979}, "southwest": {"lat": 51.53934716970849, "lng": -0.179516980291502}}}, "name": "Lotus Global Co Ltd", "place_id": "ChIJC6C-jZkadkgRb-IPHEhyubw", "types": ["point_of_interest", "store", "establishment"], "rating": 1, "user_ratings_total": 1}, "ChIJZczVvZkadkgREaZXd9B5YMc": {"geometry": {"location": {"lat": 51.539698, "lng": -0.178281}, "viewport": {"northeast": {"lat": 51.54104833029149, "lng": -0.176951519708498}, "southwest": {"lat": 51.5383503697085, "lng": -0.179649480291502}}}, "name": "ubitricity Charging Station", "place_id": "ChIJZczVvZkadkgREaZXd9B5YMc", "types": ["point_of_interest", "establishment"]}, "ChIJBSiUNJgadkgR6XqoE_XJI5Q": {"geometry": {"location": {"lat": 51.53843699999999, "lng": -0.177595}, "viewport": {"northeast": {"lat": 51.53978208029149, "lng": -0.176193769708498}, "southwest": {"lat": 51.5370841197085, "lng": -0.178891730291502}}}, "name": "ubitricity Charging Station", "place_id": "ChIJBSiUNJgadkgR6XqoE_XJI5Q", "types": ["point_of_interest", "establishment"]}, "ChIJP_ArQpgadkgR8iXxlWHsXW0": {"geometry": {"location": {"lat": 51.53737200085403, "lng": -0.1782607388735558}, "viewport": {"northeast": {"lat": 51.5387218302915, "lng": -0.176911619708498}, "southwest": {"lat": 51.53602386970851, "lng": -0.179609580291502}}}, "name": "1 Carlton Hill", "place_id": "ChIJP_ArQpgadkgR8iXxlWHsXW0", "types": ["route"]}, "ChIJb3y4QJgadkgRew46on2a4Mo": {"geometry": {"location": {"lat": 51.53749510000001, "lng": -0.1779782}, "viewport": {"northeast": {"lat": 51.53883123029151, "lng": -0.176482969708498}, "southwest": {"lat": 51.53613326970851, "lng": -0.179180930291502}}}, "name": "Laroya & Co", "place_id": "ChIJb3y4QJgadkgRew46on2a4Mo", "types": ["point_of_interest", "establishment"]}, "ChIJv9u1DLUbdkgRMx1rvJTRo98": {"geometry": {"location": {"lat": 51.537707, "lng": -0.1779389}, "viewport": {"northeast": {"lat": 51.5390443302915, "lng": -0.176439269708498}, "southwest": {"lat": 51.5363463697085, "lng": -0.1791372302915021}}}, "name": "Curious Kid", "place_id": "ChIJv9u1DLUbdkgRMx1rvJTRo98", "types": ["secondary_school", "university", "school", "point_of_interest", "establishment"], "rating": 5, "user_ratings_total": 3}, "ChIJ5QO-DZgadkgRbIynEromNlU": {"geometry": {"location": {"lat": 51.53646612212929, "lng": -0.1777710493683312}, "viewport": {"northeast": {"lat": 51.53820025000005, "lng": -0.176275619708498}, "southwest": {"lat": 51.53475524999995, "lng": -0.178973580291502}}}, "name": "1-19 Marlborough Hill", "place_id": "ChIJ5QO-DZgadkgRbIynEromNlU", "types": ["route"]}, "ChIJr-2WapgadkgRZ3sbO9zqoR0": {"geometry": {"location": {"lat": 51.5365872, "lng": -0.1781045}, "viewport": {"northeast": {"lat": 51.53794098029149, "lng": -0.176598719708498}, "southwest": {"lat": 51.5352430197085, "lng": -0.1792966802915021}}}, "name": "South Hampstead - Marlborough Hill", "place_id": "ChIJr-2WapgadkgRZ3sbO9zqoR0", "types": ["car_rental", "point_of_interest", "establishment"]}, "ChIJDQN1DZgadkgRKOs8zs6GOQ8": {"geometry": {"location": {"lat": 51.5364859, "lng": -0.177708}, "viewport": {"northeast": {"lat": 51.5378337302915, "lng": -0.176374619708498}, "southwest": {"lat": 51.5351357697085, "lng": -0.1790725802915021}}}, "name": "ubitricity Charging Station", "place_id": "ChIJDQN1DZgadkgRKOs8zs6GOQ8", "types": ["point_of_interest", "establishment"]}}}