{"E00175271": {"ChIJlTUayLkadkgRT95q0UJnn6s": {"geometry": {"location": {"lat": 51.52667913389104, "lng": -0.168206886013446}, "viewport": {"northeast": {"lat": 51.52804398029151, "lng": -0.166842219708498}, "southwest": {"lat": 51.52534601970851, "lng": -0.169540180291502}}}, "name": "13-54 Swain St", "place_id": "ChIJlTUayLkadkgRT95q0UJnn6s", "types": ["route"]}, "ChIJ0_1nx7kadkgRozQavQ886bU": {"geometry": {"location": {"lat": 51.5265737, "lng": -0.1682362}, "viewport": {"northeast": {"lat": 51.5279484802915, "lng": -0.166836919708498}, "southwest": {"lat": 51.5252505197085, "lng": -0.169534880291502}}}, "name": "Thake A", "place_id": "ChIJ0_1nx7kadkgRozQavQ886bU", "types": ["point_of_interest", "establishment"]}, "ChIJ0_1nx7kadkgRZxuqwiUrRg4": {"geometry": {"location": {"lat": 51.5265737, "lng": -0.1682362}, "viewport": {"northeast": {"lat": 51.5279484802915, "lng": -0.166836919708498}, "southwest": {"lat": 51.5252505197085, "lng": -0.169534880291502}}}, "name": "Anne's", "place_id": "ChIJ0_1nx7kadkgRZxuqwiUrRg4", "types": ["store", "point_of_interest", "establishment"]}, "ChIJi-41cvQbdkgRfYpDZuXmUAY": {"geometry": {"location": {"lat": 51.5267187, "lng": -0.1679227}, "viewport": {"northeast": {"lat": 51.5280162802915, "lng": -0.1666739697084979}, "southwest": {"lat": 51.5253183197085, "lng": -0.169371930291502}}}, "name": "Greenside community basketball court", "place_id": "ChIJi-41cvQbdkgRfYpDZuXmUAY", "types": ["point_of_interest", "establishment"], "rating": 3.3, "user_ratings_total": 6}, "ChIJsRWc4vAbdkgRfnR8S-k-MJ8": {"geometry": {"location": {"lat": 51.52695749999999, "lng": -0.1681138}, "viewport": {"northeast": {"lat": 51.5282359802915, "lng": -0.166902319708498}, "southwest": {"lat": 51.5255380197085, "lng": -0.169600280291502}}}, "name": "Lisson Green Sports Pitches and Playground", "place_id": "ChIJsRWc4vAbdkgRfnR8S-k-MJ8", "types": ["point_of_interest", "establishment"], "rating": 4.8, "user_ratings_total": 4}, "ChIJY-H_yrkadkgRdnv5hpV9FrM": {"geometry": {"location": {"lat": 51.52640090000001, "lng": -0.1676995}, "viewport": {"northeast": {"lat": 51.5277983802915, "lng": -0.166170969708498}, "southwest": {"lat": 51.5251004197085, "lng": -0.168868930291502}}}, "name": "Tresham Centre for Disabled Children & Young People", "place_id": "ChIJY-H_yrkadkgRdnv5hpV9FrM", "types": ["point_of_interest", "establishment"], "rating": 4.7, "user_ratings_total": 13}, "ChIJl3f6M7gadkgRG7r_jqjqmRE": {"geometry": {"location": {"lat": 51.52640090000001, "lng": -0.1676995}, "viewport": {"northeast": {"lat": 51.52782598029151, "lng": -0.166209469708498}, "southwest": {"lat": 51.52512801970851, "lng": -0.1689074302915021}}}, "name": "Marylebone Nursery & Pre-School", "place_id": "ChIJl3f6M7gadkgRG7r_jqjqmRE", "types": ["school", "point_of_interest", "establishment"], "rating": 3, "user_ratings_total": 2}, "ChIJ7YQskLsbdkgRXr5OW6bPwNE": {"geometry": {"location": {"lat": 51.5264503, "lng": -0.169054}, "viewport": {"northeast": {"lat": 51.5277992802915, "lng": -0.167705019708498}, "southwest": {"lat": 51.5251013197085, "lng": -0.1704029802915021}}}, "name": "Chronic Baked Delicacies", "place_id": "ChIJ7YQskLsbdkgRXr5OW6bPwNE", "types": ["bakery", "food", "point_of_interest", "store", "establishment"]}, "ChIJ2772XrcadkgRlCaD3leGrrY": {"geometry": {"location": {"lat": 51.52521865494378, "lng": -0.1692709382262759}, "viewport": {"northeast": {"lat": 51.52656813029149, "lng": -0.167921369708498}, "southwest": {"lat": 51.5238701697085, "lng": -0.170619330291502}}}, "name": "153-159 B507", "place_id": "ChIJ2772XrcadkgRlCaD3leGrrY", "types": ["route"]}, "ChIJSSGIR_sbdkgRCpLUPrfYUgA": {"geometry": {"location": {"lat": 51.52528950000001, "lng": -0.1686424}, "viewport": {"northeast": {"lat": 51.5266109802915, "lng": -0.1673468197084979}, "southwest": {"lat": 51.5239130197085, "lng": -0.170044780291502}}}, "name": "Regeneration Properties Ltd", "place_id": "ChIJSSGIR_sbdkgRCpLUPrfYUgA", "types": ["point_of_interest", "establishment"], "rating": 3, "user_ratings_total": 1}, "ChIJN7Pp3bkadkgReDmJV15Nsyw": {"geometry": {"location": {"lat": 51.5258712, "lng": -0.1686569}, "viewport": {"northeast": {"lat": 51.5272450302915, "lng": -0.1674216197084979}, "southwest": {"lat": 51.5245470697085, "lng": -0.170119580291502}}}, "name": "Turville House", "place_id": "ChIJN7Pp3bkadkgReDmJV15Nsyw", "types": ["point_of_interest", "establishment"], "rating": 4, "user_ratings_total": 1}, "ChIJ72YAMuUPdkgR-dhuGrJRtnU": {"geometry": {"location": {"lat": 51.525566, "lng": -0.1690808}, "viewport": {"northeast": {"lat": 51.5269016802915, "lng": -0.167757619708498}, "southwest": {"lat": 51.5242037197085, "lng": -0.170455580291502}}}, "name": "Bayswater Driving School", "place_id": "ChIJ72YAMuUPdkgR-dhuGrJRtnU", "types": ["point_of_interest", "establishment"], "rating": 5, "user_ratings_total": 1}, "ChIJ0--LUVsbdkgRGHAiX6IzZgo": {"geometry": {"location": {"lat": 51.52515510000001, "lng": -0.167965}, "viewport": {"northeast": {"lat": 51.52652843029151, "lng": -0.166582419708498}, "southwest": {"lat": 51.52383046970851, "lng": -0.1692803802915021}}}, "name": "Nellie Supports", "place_id": "ChIJ0--LUVsbdkgRGHAiX6IzZgo", "types": ["point_of_interest", "establishment"]}, "ChIJuRVumIkbdkgRjG_Y1VUifFE": {"geometry": {"location": {"lat": 51.52515510000001, "lng": -0.167965}, "viewport": {"northeast": {"lat": 51.52652843029151, "lng": -0.166582419708498}, "southwest": {"lat": 51.52383046970851, "lng": -0.1692803802915021}}}, "name": "Nellie Supports", "place_id": "ChIJuRVumIkbdkgRjG_Y1VUifFE", "types": ["point_of_interest", "establishment"]}, "ChIJ_Vg8fw4bdkgRiylpVZYfZek": {"geometry": {"location": {"lat": 51.5253142, "lng": -0.1690814}, "viewport": {"northeast": {"lat": 51.52660428029149, "lng": -0.167803219708498}, "southwest": {"lat": 51.5239063197085, "lng": -0.170501180291502}}}, "name": "Electrician Lisson Grove", "place_id": "ChIJ_Vg8fw4bdkgRiylpVZYfZek", "types": ["electrician", "point_of_interest", "establishment"]}, "ChIJZz8UcLcadkgRCV-f8y9-pzw": {"geometry": {"location": {"lat": 51.52468080110577, "lng": -0.1681557935169694}, "viewport": {"northeast": {"lat": 51.5260253802915, "lng": -0.166814569708498}, "southwest": {"lat": 51.5233274197085, "lng": -0.169512530291502}}}, "name": "135-141 Lisson Grove", "place_id": "ChIJZz8UcLcadkgRCV-f8y9-pzw", "types": ["route"]}, "ChIJqbxNFbcadkgRI0eOwkhzl4U": {"geometry": {"location": {"lat": 51.5241255, "lng": -0.1688334}, "viewport": {"northeast": {"lat": 51.52539763029149, "lng": -0.167568769708498}, "southwest": {"lat": 51.52269966970849, "lng": -0.170266730291502}}}, "name": "Alfies Antique Market", "place_id": "ChIJqbxNFbcadkgRI0eOwkhzl4U", "types": ["furniture_store", "home_goods_store", "point_of_interest", "store", "establishment"], "rating": 4.3, "user_ratings_total": 326}, "ChIJVXkDb7cadkgRubYcD32ouI0": {"geometry": {"location": {"lat": 51.524581, "lng": -0.168397}, "viewport": {"northeast": {"lat": 51.5259662302915, "lng": -0.167095819708498}, "southwest": {"lat": 51.5232682697085, "lng": -0.169793780291502}}}, "name": "Number One Church Street", "place_id": "ChIJVXkDb7cadkgRubYcD32ouI0", "types": ["cafe", "bar", "food", "point_of_interest", "establishment"], "rating": 4.4, "user_ratings_total": 205}, "ChIJQ6evaLcadkgRqd8B7Nkh0G4": {"geometry": {"location": {"lat": 51.5247085, "lng": -0.1687565}, "viewport": {"northeast": {"lat": 51.52600468029149, "lng": -0.167311419708498}, "southwest": {"lat": 51.52330671970849, "lng": -0.170009380291502}}}, "name": "James Worrall", "place_id": "ChIJQ6evaLcadkgRqd8B7Nkh0G4", "types": ["home_goods_store", "point_of_interest", "store", "establishment"]}, "ChIJwT-rdLcadkgR6RfwW8sW0d4": {"geometry": {"location": {"lat": 51.5244862, "lng": -0.1682866}, "viewport": {"northeast": {"lat": 51.52589433029149, "lng": -0.166820419708498}, "southwest": {"lat": 51.52319636970849, "lng": -0.169518380291502}}}, "name": "Alan Stirling Technology Ltd", "place_id": "ChIJwT-rdLcadkgR6RfwW8sW0d4", "types": ["point_of_interest", "establishment"]}, "ChIJwbbMmBkFdkgR5GbpVCyclBY": {"geometry": {"location": {"lat": 51.52445549999999, "lng": -0.1685003}, "viewport": {"northeast": {"lat": 51.5258044802915, "lng": -0.167151319708498}, "southwest": {"lat": 51.5231065197085, "lng": -0.169849280291502}}}, "name": "Retro Living", "place_id": "ChIJwbbMmBkFdkgR5GbpVCyclBY", "types": ["furniture_store", "home_goods_store", "point_of_interest", "store", "establishment"], "rating": 4.7, "user_ratings_total": 15}, "ChIJY1rCbrcadkgRrstSUfX5F88": {"geometry": {"location": {"lat": 51.524525, "lng": -0.1685196}, "viewport": {"northeast": {"lat": 51.52589973029149, "lng": -0.167209719708498}, "southwest": {"lat": 51.52320176970849, "lng": -0.169907680291502}}}, "name": "Les Couilles Du Chien", "place_id": "ChIJY1rCbrcadkgRrstSUfX5F88", "types": ["home_goods_store", "point_of_interest", "store", "establishment"], "rating": 5, "user_ratings_total": 1}, "ChIJt_vJbrcadkgRb5rjCoD7k6E": {"geometry": {"location": {"lat": 51.52448099999999, "lng": -0.1685579}, "viewport": {"northeast": {"lat": 51.52582998029149, "lng": -0.167208919708498}, "southwest": {"lat": 51.52313201970849, "lng": -0.169906880291502}}}, "name": "Philip Garrick Antiques", "place_id": "ChIJt_vJbrcadkgRb5rjCoD7k6E", "types": ["home_goods_store", "point_of_interest", "store", "establishment"]}, "ChIJl2ZhabcadkgR25AQxQYRS34": {"geometry": {"location": {"lat": 51.52441779999999, "lng": -0.1686705}, "viewport": {"northeast": {"lat": 51.52579093029149, "lng": -0.167365519708498}, "southwest": {"lat": 51.52309296970849, "lng": -0.170063480291502}}}, "name": "Patrick Heide Contemporary Art", "place_id": "ChIJl2ZhabcadkgR25AQxQYRS34", "types": ["art_gallery", "tourist_attraction", "point_of_interest", "establishment"], "rating": 4.5, "user_ratings_total": 2}, "ChIJ7cyta7cadkgRVQv07Daw9Ig": {"geometry": {"location": {"lat": 51.52428629999999, "lng": -0.1687705}, "viewport": {"northeast": {"lat": 51.5256270302915, "lng": -0.167407969708498}, "southwest": {"lat": 51.5229290697085, "lng": -0.170105930291502}}}, "name": "Handmade by You", "place_id": "ChIJ7cyta7cadkgRVQv07Daw9Ig", "types": ["point_of_interest", "establishment"]}, "ChIJs__uQrcadkgRJaqPi_cWrkc": {"geometry": {"location": {"lat": 51.5245688, "lng": -0.1688589}, "viewport": {"northeast": {"lat": 51.5259468802915, "lng": -0.167696769708498}, "southwest": {"lat": 51.5232489197085, "lng": -0.170394730291502}}}, "name": "Newpin!!!", "place_id": "ChIJs__uQrcadkgRJaqPi_cWrkc", "types": ["school", "point_of_interest", "establishment"], "rating": 5, "user_ratings_total": 4}, "ChIJqbxNFbcadkgRSbLP1KK7jRQ": {"geometry": {"location": {"lat": 51.5243153, "lng": -0.1688275}, "viewport": {"northeast": {"lat": 51.5256776802915, "lng": -0.167520819708498}, "southwest": {"lat": 51.5229797197085, "lng": -0.170218780291502}}}, "name": "Clive", "place_id": "ChIJqbxNFbcadkgRSbLP1KK7jRQ", "types": ["point_of_interest", "establishment"]}, "ChIJ55lDaLcadkgRd1AMo06sEt4": {"geometry": {"location": {"lat": 51.5246445, "lng": -0.1688501}, "viewport": {"northeast": {"lat": 51.5259402802915, "lng": -0.167404269708498}, "southwest": {"lat": 51.5232423197085, "lng": -0.170102230291502}}}, "name": "Retrospective Interiors", "place_id": "ChIJ55lDaLcadkgRd1AMo06sEt4", "types": ["home_goods_store", "point_of_interest", "store", "establishment"], "rating": 5, "user_ratings_total": 2}, "ChIJwbO8abcadkgRrW7T7PzmRhw": {"geometry": {"location": {"lat": 51.5245933, "lng": -0.168926}, "viewport": {"northeast": {"lat": 51.52588858029149, "lng": -0.167479219708498}, "southwest": {"lat": 51.5231906197085, "lng": -0.170177180291502}}}, "name": "Shepherds Bush Housing Association", "place_id": "ChIJwbO8abcadkgRrW7T7PzmRhw", "types": ["local_government_office", "point_of_interest", "establishment"], "rating": 1, "user_ratings_total": 1}, "ChIJG6be6ywFdkgRVgVKBNMdfMk": {"geometry": {"location": {"lat": 51.5241887, "lng": -0.1688101}, "viewport": {"northeast": {"lat": 51.5255938302915, "lng": -0.167560819708498}, "southwest": {"lat": 51.52289586970851, "lng": -0.170258780291502}}}, "name": "Linda Bee", "place_id": "ChIJG6be6ywFdkgRVgVKBNMdfMk", "types": ["home_goods_store", "point_of_interest", "store", "establishment"], "rating": 5, "user_ratings_total": 2}, "ChIJ-__jarcadkgRs3y32-dyBqU": {"geometry": {"location": {"lat": 51.5241888, "lng": -0.16881}, "viewport": {"northeast": {"lat": 51.5255939302915, "lng": -0.167560719708498}, "southwest": {"lat": 51.5228959697085, "lng": -0.170258680291502}}}, "name": "MARTIN-ROONEY.COM", "place_id": "ChIJ-__jarcadkgRs3y32-dyBqU", "types": ["furniture_store", "home_goods_store", "point_of_interest", "store", "establishment"]}, "ChIJ___jarcadkgR07SVVbFq99c": {"geometry": {"location": {"lat": 51.5241887, "lng": -0.1688101}, "viewport": {"northeast": {"lat": 51.5255938302915, "lng": -0.167560819708498}, "southwest": {"lat": 51.52289586970851, "lng": -0.170258780291502}}}, "name": "Martinez Negrillo Antiques", "place_id": "ChIJ___jarcadkgR07SVVbFq99c", "types": ["home_goods_store", "point_of_interest", "store", "establishment"], "rating": 5, "user_ratings_total": 5}, "ChIJXUWJarcadkgR_92rK5NzEgs": {"geometry": {"location": {"lat": 51.5241887, "lng": -0.1688101}, "viewport": {"northeast": {"lat": 51.5255815802915, "lng": -0.167536969708498}, "southwest": {"lat": 51.5228836197085, "lng": -0.170234930291502}}}, "name": "The Moderns", "place_id": "ChIJXUWJarcadkgR_92rK5NzEgs", "types": ["furniture_store", "home_goods_store", "point_of_interest", "store", "establishment"], "rating": 3.5, "user_ratings_total": 2}, "ChIJpRDYarcadkgRU9s3M57OB-0": {"geometry": {"location": {"lat": 51.5241639, "lng": -0.1687778}, "viewport": {"northeast": {"lat": 51.5255747302915, "lng": -0.167546519708498}, "southwest": {"lat": 51.5228767697085, "lng": -0.170244480291502}}}, "name": "Quad", "place_id": "ChIJpRDYarcadkgRU9s3M57OB-0", "types": ["point_of_interest", "establishment"]}, "ChIJ--BlkywFdkgRZMJGyYy8aLs": {"geometry": {"location": {"lat": 51.5241568, "lng": -0.1690248}, "viewport": {"northeast": {"lat": 51.5255732302915, "lng": -0.167648119708498}, "southwest": {"lat": 51.5228752697085, "lng": -0.170346080291502}}}, "name": "Gillian Horsup", "place_id": "ChIJ--BlkywFdkgRZMJGyYy8aLs", "types": ["jewelry_store", "home_goods_store", "point_of_interest", "clothing_store", "store", "establishment"], "rating": 5, "user_ratings_total": 22}, "ChIJW-XRZ7cadkgRvb_hAF8Gg2U": {"geometry": {"location": {"lat": 51.5247818, "lng": -0.1688168}, "viewport": {"northeast": {"lat": 51.5260049802915, "lng": -0.167675719708498}, "southwest": {"lat": 51.5233070197085, "lng": -0.170373680291502}}}, "name": "Church Street Nursery", "place_id": "ChIJW-XRZ7cadkgRvb_hAF8Gg2U", "types": ["school", "point_of_interest", "establishment"], "rating": 5, "user_ratings_total": 1}, "ChIJqbxNFbcadkgR6JvqlN0B5_Y": {"geometry": {"location": {"lat": 51.5241523, "lng": -0.168852}, "viewport": {"northeast": {"lat": 51.5255709802915, "lng": -0.167605769708498}, "southwest": {"lat": 51.5228730197085, "lng": -0.170303730291502}}}, "name": "Wordville", "place_id": "ChIJqbxNFbcadkgR6JvqlN0B5_Y", "types": ["point_of_interest", "establishment"], "rating": 3, "user_ratings_total": 2}, "ChIJqbxNFbcadkgRn_wCjf2BfIc": {"geometry": {"location": {"lat": 51.524127, "lng": -0.1688328}, "viewport": {"northeast": {"lat": 51.5255583302915, "lng": -0.167602469708498}, "southwest": {"lat": 51.5228603697085, "lng": -0.170300430291502}}}, "name": "SyrupBucketRecords", "place_id": "ChIJqbxNFbcadkgRn_wCjf2BfIc", "types": ["home_goods_store", "point_of_interest", "store", "establishment"]}, "ChIJSTy25r4BdkgR_0Eu4AmkD-s": {"geometry": {"location": {"lat": 51.5241255, "lng": -0.1688334}, "viewport": {"northeast": {"lat": 51.5255246302915, "lng": -0.167585769708498}, "southwest": {"lat": 51.5228266697085, "lng": -0.170283730291502}}}, "name": "Arabella Bianco", "place_id": "ChIJSTy25r4BdkgR_0Eu4AmkD-s", "types": ["jewelry_store", "home_goods_store", "point_of_interest", "store", "establishment"], "rating": 5, "user_ratings_total": 7}, "ChIJv_aVbrcadkgR7vpNOPYacvc": {"geometry": {"location": {"lat": 51.524127, "lng": -0.1688328}, "viewport": {"northeast": {"lat": 51.5255583302915, "lng": -0.167602469708498}, "southwest": {"lat": 51.5228603697085, "lng": -0.170300430291502}}}, "name": "Modo Italia", "place_id": "ChIJv_aVbrcadkgR7vpNOPYacvc", "types": ["point_of_interest", "establishment"]}, "ChIJy_3ParcadkgR66ohUQrBazs": {"geometry": {"location": {"lat": 51.5241255, "lng": -0.1688334}, "viewport": {"northeast": {"lat": 51.5255575802915, "lng": -0.167603469708498}, "southwest": {"lat": 51.5228596197085, "lng": -0.170301430291502}}}, "name": "Paola Bazzoli", "place_id": "ChIJy_3ParcadkgR66ohUQrBazs", "types": ["point_of_interest", "establishment"]}, "ChIJTbtNFbcadkgRW9OEGm2sMGw": {"geometry": {"location": {"lat": 51.5242137, "lng": -0.1689728}, "viewport": {"northeast": {"lat": 51.5255921802915, "lng": -0.167613569708498}, "southwest": {"lat": 51.5228942197085, "lng": -0.170311530291502}}}, "name": "Stephen Lazarus", "place_id": "ChIJTbtNFbcadkgRW9OEGm2sMGw", "types": ["home_goods_store", "point_of_interest", "store", "establishment"], "rating": 5, "user_ratings_total": 1}, "ChIJu8uiarcadkgRblHiOYw3b_Q": {"geometry": {"location": {"lat": 51.5241705, "lng": -0.1689336}, "viewport": {"northeast": {"lat": 51.5255599302915, "lng": -0.167622269708498}, "southwest": {"lat": 51.5228619697085, "lng": -0.170320230291502}}}, "name": "Charles Fine Art", "place_id": "ChIJu8uiarcadkgRblHiOYw3b_Q", "types": ["art_gallery", "point_of_interest", "establishment"]}, "ChIJP_F1QbcadkgRavaL-GiYtwY": {"geometry": {"location": {"lat": 51.524399, "lng": -0.1691282}, "viewport": {"northeast": {"lat": 51.5257479802915, "lng": -0.167779219708498}, "southwest": {"lat": 51.5230500197085, "lng": -0.170477180291502}}}, "name": "Young & Son", "place_id": "ChIJP_F1QbcadkgRavaL-GiYtwY", "types": ["store", "point_of_interest", "establishment"]}, "ChIJ500hDbcadkgRWmzjkwHwilk": {"geometry": {"location": {"lat": 51.52403529999999, "lng": -0.1680479}, "viewport": {"northeast": {"lat": 51.52538878029149, "lng": -0.166689569708498}, "southwest": {"lat": 51.52269081970849, "lng": -0.169387530291502}}}, "name": "Altiplano Finance Limited", "place_id": "ChIJ500hDbcadkgRWmzjkwHwilk", "types": ["finance", "point_of_interest", "establishment"]}, "ChIJG8-oarcadkgR7wX00QmA2ZU": {"geometry": {"location": {"lat": 51.52412, "lng": -0.16895}, "viewport": {"northeast": {"lat": 51.5255548302915, "lng": -0.167646119708498}, "southwest": {"lat": 51.52285686970851, "lng": -0.170344080291502}}}, "name": "Kingsman", "place_id": "ChIJG8-oarcadkgR7wX00QmA2ZU", "types": ["moving_company", "storage", "point_of_interest", "establishment"], "rating": 3.8, "user_ratings_total": 5}, "ChIJMZT4N7cadkgRCLd59y666Pc": {"geometry": {"location": {"lat": 51.5243638, "lng": -0.1691784}, "viewport": {"northeast": {"lat": 51.5256725302915, "lng": -0.167757919708498}, "southwest": {"lat": 51.5229745697085, "lng": -0.170455880291502}}}, "name": "Hudson Grove Antiques", "place_id": "ChIJMZT4N7cadkgRCLd59y666Pc", "types": ["home_goods_store", "point_of_interest", "store", "establishment"]}, "ChIJ2UNxQbcadkgRwvW0Od6QN64": {"geometry": {"location": {"lat": 51.524356, "lng": -0.169184}, "viewport": {"northeast": {"lat": 51.5257049802915, "lng": -0.167835019708498}, "southwest": {"lat": 51.5230070197085, "lng": -0.1705329802915021}}}, "name": "Rare Rugs", "place_id": "ChIJ2UNxQbcadkgRwvW0Od6QN64", "types": ["point_of_interest", "store", "establishment"]}, "ChIJTbtNFbcadkgRCB7kuwYMquo": {"geometry": {"location": {"lat": 51.5240296, "lng": -0.1687804}, "viewport": {"northeast": {"lat": 51.52536973029149, "lng": -0.167417419708498}, "southwest": {"lat": 51.5226717697085, "lng": -0.170115380291502}}}, "name": "Christopher Hall", "place_id": "ChIJTbtNFbcadkgRCB7kuwYMquo", "types": ["home_goods_store", "point_of_interest", "store", "establishment"]}, "ChIJtzrlQ7cadkgRVCG9_EaiPhs": {"geometry": {"location": {"lat": 51.52457, "lng": -0.169129}, "viewport": {"northeast": {"lat": 51.5258488302915, "lng": -0.167620619708498}, "southwest": {"lat": 51.52315086970851, "lng": -0.170318580291502}}}, "name": "Original Lahore", "place_id": "ChIJtzrlQ7cadkgRVCG9_EaiPhs", "types": ["meal_takeaway", "restaurant", "food", "point_of_interest", "establishment"], "rating": 3.7, "user_ratings_total": 422}, "ChIJaa3hFLcadkgRns0e24FR3wc": {"geometry": {"location": {"lat": 51.5240045, "lng": -0.1687555}, "viewport": {"northeast": {"lat": 51.5253405302915, "lng": -0.167387269708498}, "southwest": {"lat": 51.5226425697085, "lng": -0.170085230291502}}}, "name": "Robinson Antiques", "place_id": "ChIJaa3hFLcadkgRns0e24FR3wc", "types": ["home_goods_store", "point_of_interest", "store", "establishment"], "rating": 3, "user_ratings_total": 3}, "ChIJDUNWaLcadkgRCQz4hrlHFR4": {"geometry": {"location": {"lat": 51.5246445, "lng": -0.1688501}, "viewport": {"northeast": {"lat": 51.5259402802915, "lng": -0.167404269708498}, "southwest": {"lat": 51.5232423197085, "lng": -0.170102230291502}}}, "name": "Marylebone Antiques (Formerly Church Street Antiques)", "place_id": "ChIJDUNWaLcadkgRCQz4hrlHFR4", "types": ["home_goods_store", "point_of_interest", "store", "establishment"], "rating": 4.7, "user_ratings_total": 7}, "ChIJnW512LAadkgR7PK4ONYVxDY": {"geometry": {"location": {"lat": 51.5243626, "lng": -0.1692367}, "viewport": {"northeast": {"lat": 51.5256625302915, "lng": -0.167800669708498}, "southwest": {"lat": 51.52296456970851, "lng": -0.170498630291502}}}, "name": "Caribbean Steel Band", "place_id": "ChIJnW512LAadkgR7PK4ONYVxDY", "types": ["electronics_store", "home_goods_store", "point_of_interest", "store", "establishment"]}, "ChIJkcyAC-QadkgRVWMTgDcWd5s": {"geometry": {"location": {"lat": 51.5241377, "lng": -0.168796}, "viewport": {"northeast": {"lat": 51.5255636802915, "lng": -0.167571019708498}, "southwest": {"lat": 51.52286571970851, "lng": -0.170268980291502}}}, "name": "Planet Bazaar", "place_id": "ChIJkcyAC-QadkgRVWMTgDcWd5s", "types": ["art_gallery", "home_goods_store", "point_of_interest", "store", "establishment"], "rating": 2.1, "user_ratings_total": 10}, "ChIJR0GwQbcadkgR1hOq1JAt4T0": {"geometry": {"location": {"lat": 51.52402939999999, "lng": -0.1688724}, "viewport": {"northeast": {"lat": 51.5255020802915, "lng": -0.167660169708498}, "southwest": {"lat": 51.5228041197085, "lng": -0.170358130291502}}}, "name": "Louise Verber Antiques", "place_id": "ChIJR0GwQbcadkgR1hOq1JAt4T0", "types": ["home_goods_store", "point_of_interest", "store", "establishment"]}, "ChIJqbxNFbcadkgR33P2SsnKTBM": {"geometry": {"location": {"lat": 51.52417490000001, "lng": -0.1687428}, "viewport": {"northeast": {"lat": 51.52558673029149, "lng": -0.167509269708498}, "southwest": {"lat": 51.52288876970849, "lng": -0.170207230291502}}}, "name": "Alfies Roof Top Kitchen.", "place_id": "ChIJqbxNFbcadkgR33P2SsnKTBM", "types": ["cafe", "restaurant", "food", "point_of_interest", "establishment"], "rating": 4.5, "user_ratings_total": 115}, "ChIJ3VHNJdUbdkgRzIP1tbAE5U4": {"geometry": {"location": {"lat": 51.52445549999999, "lng": -0.1685003}, "viewport": {"northeast": {"lat": 51.5258466802915, "lng": -0.167228119708498}, "southwest": {"lat": 51.5231487197085, "lng": -0.169926080291502}}}, "name": "TY Solutions", "place_id": "ChIJ3VHNJdUbdkgRzIP1tbAE5U4", "types": ["laundry", "point_of_interest", "establishment"]}, "ChIJwT-rdLcadkgRFYEDyvh20qo": {"geometry": {"location": {"lat": 51.5244862, "lng": -0.1682866}, "viewport": {"northeast": {"lat": 51.52589433029149, "lng": -0.166820419708498}, "southwest": {"lat": 51.52319636970849, "lng": -0.169518380291502}}}, "name": "Eileen Stirling Designs", "place_id": "ChIJwT-rdLcadkgRFYEDyvh20qo", "types": ["home_goods_store", "general_contractor", "point_of_interest", "store", "establishment"]}, "ChIJJaMbt7AcdkgRShrK8zvuWS8": {"geometry": {"location": {"lat": 51.5245606, "lng": -0.1683696}, "viewport": {"northeast": {"lat": 51.52594893029151, "lng": -0.167092219708498}, "southwest": {"lat": 51.52325096970851, "lng": -0.169790180291502}}}, "name": "Stratford Rooms", "place_id": "ChIJJaMbt7AcdkgRShrK8zvuWS8", "types": ["lodging", "point_of_interest", "establishment"], "rating": 1, "user_ratings_total": 1}, "ChIJjd1NbrcadkgRXsL8yKCEJIA": {"geometry": {"location": {"lat": 51.5245606, "lng": -0.1683695}, "viewport": {"northeast": {"lat": 51.52594893029151, "lng": -0.167092169708498}, "southwest": {"lat": 51.52325096970851, "lng": -0.169790130291502}}}, "name": "Conteh", "place_id": "ChIJjd1NbrcadkgRXsL8yKCEJIA", "types": ["convenience_store", "food", "point_of_interest", "store", "establishment"]}, "ChIJdc8db7cadkgRSoN6rI5R2z4": {"geometry": {"location": {"lat": 51.5245806, "lng": -0.1683969}, "viewport": {"northeast": {"lat": 51.5259603302915, "lng": -0.167103869708498}, "southwest": {"lat": 51.5232623697085, "lng": -0.169801830291502}}}, "name": "Manash", "place_id": "ChIJdc8db7cadkgRSoN6rI5R2z4", "types": ["point_of_interest", "establishment"]}, "ChIJk-9RabcadkgRQBcgUYesqXc": {"geometry": {"location": {"lat": 51.5244531, "lng": -0.168631}, "viewport": {"northeast": {"lat": 51.5258246302915, "lng": -0.167323019708498}, "southwest": {"lat": 51.5231266697085, "lng": -0.170020980291502}}}, "name": "Brocantry", "place_id": "ChIJk-9RabcadkgRQBcgUYesqXc", "types": ["point_of_interest", "establishment"]}, "ChIJWQ8SN7cadkgRzlI8ew10sEM": {"geometry": {"location": {"lat": 51.5243954, "lng": -0.1686488}, "viewport": {"northeast": {"lat": 51.5257767802915, "lng": -0.1673588197084979}, "southwest": {"lat": 51.5230788197085, "lng": -0.170056780291502}}}, "name": "Harvey Management Services Ltd", "place_id": "ChIJWQ8SN7cadkgRzlI8ew10sEM", "types": ["home_goods_store", "point_of_interest", "store", "establishment"], "rating": 5, "user_ratings_total": 1}, "ChIJz30aHS8bdkgRX3byN7L8_HU": {"geometry": {"location": {"lat": 51.5246067, "lng": -0.1686062}, "viewport": {"northeast": {"lat": 51.52596193029149, "lng": -0.167268669708498}, "southwest": {"lat": 51.5232639697085, "lng": -0.169966630291502}}}, "name": "Interior Boutiques", "place_id": "ChIJz30aHS8bdkgRX3byN7L8_HU", "types": ["home_goods_store", "point_of_interest", "store", "establishment"]}, "ChIJoZRTcLcadkgRaDCaVV-VIPg": {"geometry": {"location": {"lat": 51.524483, "lng": -0.1680181000000001}, "viewport": {"northeast": {"lat": 51.5258496802915, "lng": -0.166630269708498}, "southwest": {"lat": 51.5231517197085, "lng": -0.169328230291502}}}, "name": "ubitricity Charging Station", "place_id": "ChIJoZRTcLcadkgRaDCaVV-VIPg", "types": ["point_of_interest", "establishment"]}, "ChIJDb7P60kbdkgRad9naTfakcA": {"geometry": {"location": {"lat": 51.5243435, "lng": -0.1687478}, "viewport": {"northeast": {"lat": 51.5256924802915, "lng": -0.167398819708498}, "southwest": {"lat": 51.5229945197085, "lng": -0.170096780291502}}}, "name": "Al Fayez", "place_id": "ChIJDb7P60kbdkgRad9naTfakcA", "types": ["home_goods_store", "point_of_interest", "store", "establishment"], "rating": 5, "user_ratings_total": 3}, "ChIJ1eOiEbQbdkgRABqlFWpja8A": {"geometry": {"location": {"lat": 51.52434119999999, "lng": -0.1687512}, "viewport": {"northeast": {"lat": 51.52572153029149, "lng": -0.167451769708498}, "southwest": {"lat": 51.52302356970849, "lng": -0.170149730291502}}}, "name": "GRIFFIN ART", "place_id": "ChIJ1eOiEbQbdkgRABqlFWpja8A", "types": ["home_goods_store", "point_of_interest", "store", "establishment"]}, "ChIJbSk1arcadkgRjDdoYxpt2LM": {"geometry": {"location": {"lat": 51.5243376, "lng": -0.1687823}, "viewport": {"northeast": {"lat": 51.5256777802915, "lng": -0.167446719708498}, "southwest": {"lat": 51.5229798197085, "lng": -0.170144680291502}}}, "name": "Symphony of Shadows - Dressmaker", "place_id": "ChIJbSk1arcadkgRjDdoYxpt2LM", "types": ["point_of_interest", "establishment"]}, "ChIJxbA39BsbdkgRSoIivtj5iTQ": {"geometry": {"location": {"lat": 51.5246701, "lng": -0.1688122}, "viewport": {"northeast": {"lat": 51.5259779802915, "lng": -0.167349919708498}, "southwest": {"lat": 51.5232800197085, "lng": -0.1700478802915021}}}, "name": "Living In Style Gallery", "place_id": "ChIJxbA39BsbdkgRSoIivtj5iTQ", "types": ["furniture_store", "home_goods_store", "point_of_interest", "store", "establishment"], "rating": 5, "user_ratings_total": 9}, "ChIJFZqcpuQQdkgRw0gvw7IDrjc": {"geometry": {"location": {"lat": 51.5246997, "lng": -0.1687729}, "viewport": {"northeast": {"lat": 51.5259952802915, "lng": -0.167326719708498}, "southwest": {"lat": 51.5232973197085, "lng": -0.170024680291502}}}, "name": "Aaron Nejad Gallery", "place_id": "ChIJFZqcpuQQdkgRw0gvw7IDrjc", "types": ["home_goods_store", "point_of_interest", "store", "establishment"], "rating": 3, "user_ratings_total": 1}, "ChIJGTKQQ7cadkgRMMD-Nqhli44": {"geometry": {"location": {"lat": 51.5245012, "lng": -0.1689285}, "viewport": {"northeast": {"lat": 51.5258162802915, "lng": -0.167517769708498}, "southwest": {"lat": 51.5231183197085, "lng": -0.170215730291502}}}, "name": "The Salon Collective", "place_id": "ChIJGTKQQ7cadkgRMMD-Nqhli44", "types": ["university", "point_of_interest", "establishment"], "rating": 5, "user_ratings_total": 25}, "ChIJibxcarcadkgRK9p14xYHTDc": {"geometry": {"location": {"lat": 51.52429009999999, "lng": -0.1688628}, "viewport": {"northeast": {"lat": 51.5256597302915, "lng": -0.167528669708498}, "southwest": {"lat": 51.52296176970851, "lng": -0.170226630291502}}}, "name": "Moe Heidarieh", "place_id": "ChIJibxcarcadkgRK9p14xYHTDc", "types": ["point_of_interest", "establishment"]}, "ChIJ___jarcadkgRosTgVXuY73s": {"geometry": {"location": {"lat": 51.52425280000001, "lng": -0.168848}, "viewport": {"northeast": {"lat": 51.5256376302915, "lng": -0.167562669708498}, "southwest": {"lat": 51.52293966970851, "lng": -0.170260630291502}}}, "name": "William Campbell Fine Frames and Framing", "place_id": "ChIJ___jarcadkgRosTgVXuY73s", "types": ["point_of_interest", "store", "establishment"], "rating": 4.9, "user_ratings_total": 9}, "ChIJ-__jarcadkgRnY4Q483kHw0": {"geometry": {"location": {"lat": 51.5241888, "lng": -0.16881}, "viewport": {"northeast": {"lat": 51.5255939302915, "lng": -0.167560719708498}, "southwest": {"lat": 51.5228959697085, "lng": -0.170258680291502}}}, "name": "Sambataro", "place_id": "ChIJ-__jarcadkgRnY4Q483kHw0", "types": ["point_of_interest", "establishment"], "rating": 5, "user_ratings_total": 1}, "ChIJxXVXErcadkgRdHFpFGQzUaE": {"geometry": {"location": {"lat": 51.5239116, "lng": -0.168376}, "viewport": {"northeast": {"lat": 51.52529038029149, "lng": -0.166979019708498}, "southwest": {"lat": 51.5225924197085, "lng": -0.169676980291502}}}, "name": "Call Handling Services", "place_id": "ChIJxXVXErcadkgRdHFpFGQzUaE", "types": ["point_of_interest", "establishment"]}, "ChIJY96F6LkadkgRSKkMqu-ngAQ": {"geometry": {"location": {"lat": 51.52642147879727, "lng": -0.1691981104193548}, "viewport": {"northeast": {"lat": 51.5275976802915, "lng": -0.16780575}, "southwest": {"lat": 51.5248997197085, "lng": -0.17059875}}}, "name": "1-13 Jerome Cres", "place_id": "ChIJY96F6LkadkgRSKkMqu-ngAQ", "types": ["route"]}, "ChIJG1phH7oadkgRulYuq25vZxU": {"geometry": {"location": {"lat": 51.52669409999999, "lng": -0.1707129}, "viewport": {"northeast": {"lat": 51.52804308029149, "lng": -0.169363919708498}, "southwest": {"lat": 51.52534511970849, "lng": -0.172061880291502}}}, "name": "Lisson Grove Mooring", "place_id": "ChIJG1phH7oadkgRulYuq25vZxU", "types": ["point_of_interest", "establishment"], "rating": 4.4, "user_ratings_total": 11}, "ChIJKYso_7kadkgReO2tRTHKsT4": {"geometry": {"location": {"lat": 51.52567593827767, "lng": -0.1702564495664451}, "viewport": {"northeast": {"lat": 51.5270265802915, "lng": -0.168905469708498}, "southwest": {"lat": 51.5243286197085, "lng": -0.171603430291502}}}, "name": "169-199 B507", "place_id": "ChIJKYso_7kadkgReO2tRTHKsT4", "types": ["route"]}, "ChIJLQlEELoadkgRhbM1HBQfsbU": {"geometry": {"location": {"lat": 51.5253522, "lng": -0.1702346}, "viewport": {"northeast": {"lat": 51.52680263029151, "lng": -0.168765119708498}, "southwest": {"lat": 51.52410466970851, "lng": -0.171463080291502}}}, "name": "STAMPE & STAMPE HANDYMAN SERVICES", "place_id": "ChIJLQlEELoadkgRhbM1HBQfsbU", "types": ["painter", "general_contractor", "point_of_interest", "establishment"]}, "ChIJFZS0s7AadkgRdDpdrwM3XuE": {"geometry": {"location": {"lat": 51.52559, "lng": -0.171004}, "viewport": {"northeast": {"lat": 51.5269389802915, "lng": -0.169655019708498}, "southwest": {"lat": 51.5242410197085, "lng": -0.172352980291502}}}, "name": "Gateway Academy", "place_id": "ChIJFZS0s7AadkgRdDpdrwM3XuE", "types": ["primary_school", "school", "point_of_interest", "establishment"], "rating": 4.5, "user_ratings_total": 17}, "ChIJY-3Q-bkadkgRXeilzQ9UA6k": {"geometry": {"location": {"lat": 51.5260272, "lng": -0.1702305}, "viewport": {"northeast": {"lat": 51.52738143029149, "lng": -0.168716119708498}, "southwest": {"lat": 51.52468346970849, "lng": -0.171414080291502}}}, "name": "Skyrocket Your Search", "place_id": "ChIJY-3Q-bkadkgRXeilzQ9UA6k", "types": ["point_of_interest", "establishment"], "rating": 5, "user_ratings_total": 1}, "ChIJ6-IIAroadkgRfm4cUYF2t78": {"geometry": {"location": {"lat": 51.5257775, "lng": -0.1704675}, "viewport": {"northeast": {"lat": 51.5271001802915, "lng": -0.169150269708498}, "southwest": {"lat": 51.5244022197085, "lng": -0.171848230291502}}}, "name": "Frampton Street", "place_id": "ChIJ6-IIAroadkgRfm4cUYF2t78", "types": ["transit_station", "point_of_interest", "establishment"]}, "ChIJkVkX_7kadkgRGh0Ukw8oyZQ": {"geometry": {"location": {"lat": 51.525627, "lng": -0.170315}, "viewport": {"northeast": {"lat": 51.5270005302915, "lng": -0.1689369197084979}, "southwest": {"lat": 51.5243025697085, "lng": -0.171634880291502}}}, "name": "Frampton Street (Stop LR)", "place_id": "ChIJkVkX_7kadkgRGh0Ukw8oyZQ", "types": ["transit_station", "point_of_interest", "establishment"]}, "ChIJrWtlH_gbdkgRSvLrA18VGg4": {"geometry": {"location": {"lat": 51.52545569999999, "lng": -0.1701972}, "viewport": {"northeast": {"lat": 51.5268670802915, "lng": -0.168774069708498}, "southwest": {"lat": 51.5241691197085, "lng": -0.171472030291502}}}, "name": "Belvedere Heights", "place_id": "ChIJrWtlH_gbdkgRSvLrA18VGg4", "types": ["point_of_interest", "establishment"]}, "ChIJpeUCohMbdkgRp9P_2pol2pk": {"geometry": {"location": {"lat": 51.5259189, "lng": -0.1706046}, "viewport": {"northeast": {"lat": 51.5272424802915, "lng": -0.169286819708498}, "southwest": {"lat": 51.5245445197085, "lng": -0.171984780291502}}}, "name": "College", "place_id": "ChIJpeUCohMbdkgRp9P_2pol2pk", "types": ["school", "point_of_interest", "establishment"]}, "ChIJx7j8AroadkgRCQdP4teBgVk": {"geometry": {"location": {"lat": 51.525928, "lng": -0.17062}, "viewport": {"northeast": {"lat": 51.5272510302915, "lng": -0.169302919708498}, "southwest": {"lat": 51.5245530697085, "lng": -0.172000880291502}}}, "name": "Frampton Street (Stop LH)", "place_id": "ChIJx7j8AroadkgRCQdP4teBgVk", "types": ["transit_station", "point_of_interest", "establishment"], "rating": 5, "user_ratings_total": 1}, "ChIJgxxqwc0bdkgRtDEHq7TeVeM": {"geometry": {"location": {"lat": 51.52604059999999, "lng": -0.1703236}, "viewport": {"northeast": {"lat": 51.52738143029149, "lng": -0.1687626697084979}, "southwest": {"lat": 51.52468346970849, "lng": -0.171460630291502}}}, "name": "Meu jardin Particular", "place_id": "ChIJgxxqwc0bdkgRtDEHq7TeVeM", "types": ["lodging", "point_of_interest", "establishment"]}, "ChIJO-BKBLoadkgRkWM1pPzEytg": {"geometry": {"location": {"lat": 51.5258489, "lng": -0.1710512}, "viewport": {"northeast": {"lat": 51.52716689194794, "lng": -0.1696497893191325}, "southwest": {"lat": 51.52446893136494, "lng": -0.1723477499021365}}}, "name": "Parking lot", "place_id": "ChIJO-BKBLoadkgRkWM1pPzEytg", "types": ["parking", "premise", "point_of_interest", "establishment"]}, "ChIJP7gqs7AadkgR-NehOlJOOKw": {"geometry": {"location": {"lat": 51.52443595019658, "lng": -0.170589950763427}, "viewport": {"northeast": {"lat": 51.52578493029149, "lng": -0.169240969708498}, "southwest": {"lat": 51.52308696970849, "lng": -0.171938930291502}}}, "name": "10 Capland St", "place_id": "ChIJP7gqs7AadkgR-NehOlJOOKw", "types": ["route"]}, "ChIJQ_UHRbcadkgR4v1aHkoyGuc": {"geometry": {"location": {"lat": 51.524475, "lng": -0.169555}, "viewport": {"northeast": {"lat": 51.5259022802915, "lng": -0.168152969708498}, "southwest": {"lat": 51.5232043197085, "lng": -0.1708509302915021}}}, "name": "The Cockpit", "place_id": "ChIJQ_UHRbcadkgR4v1aHkoyGuc", "types": ["point_of_interest", "establishment"], "rating": 4.4, "user_ratings_total": 364}, "ChIJ6SK4T7cadkgRjvMK0cdduD4": {"geometry": {"location": {"lat": 51.5246881, "lng": -0.1698299}, "viewport": {"northeast": {"lat": 51.52602768029151, "lng": -0.168543719708498}, "southwest": {"lat": 51.52332971970851, "lng": -0.171241680291502}}}, "name": "Marylebone Bangladesh Society", "place_id": "ChIJ6SK4T7cadkgRjvMK0cdduD4", "types": ["point_of_interest", "establishment"], "rating": 5, "user_ratings_total": 1}, "ChIJD_UjQbcadkgRXouM7oeAE2U": {"geometry": {"location": {"lat": 51.52440920000001, "lng": -0.1695107}, "viewport": {"northeast": {"lat": 51.5258461802915, "lng": -0.168064719708498}, "southwest": {"lat": 51.5231482197085, "lng": -0.170762680291502}}}, "name": "Farah UK Ltd", "place_id": "ChIJD_UjQbcadkgRXouM7oeAE2U", "types": ["clothing_store", "point_of_interest", "store", "establishment"], "rating": 5, "user_ratings_total": 1}, "ChIJs_ccRbcadkgRUX-vW_ocGwY": {"geometry": {"location": {"lat": 51.52461330000001, "lng": -0.1695597}, "viewport": {"northeast": {"lat": 51.52598193029149, "lng": -0.168187069708498}, "southwest": {"lat": 51.52328396970849, "lng": -0.170885030291502}}}, "name": "Dr A A Bakker - Lisson Grove Health Centre", "place_id": "ChIJs_ccRbcadkgRUX-vW_ocGwY", "types": ["doctor", "health", "point_of_interest", "establishment"], "rating": 2, "user_ratings_total": 4}, "ChIJMWkwR7cadkgRncoga9iH6Cg": {"geometry": {"location": {"lat": 51.5242186, "lng": -0.1694428}, "viewport": {"northeast": {"lat": 51.52551793029151, "lng": -0.168007269708498}, "southwest": {"lat": 51.52281996970851, "lng": -0.170705230291502}}}, "name": "Norwegian Log Buildings", "place_id": "ChIJMWkwR7cadkgRncoga9iH6Cg", "types": ["point_of_interest", "establishment"]}, "ChIJz_KwOLcadkgRs1D0J8syUxU": {"geometry": {"location": {"lat": 51.5241026, "lng": -0.1695451}, "viewport": {"northeast": {"lat": 51.5254515802915, "lng": -0.168196119708498}, "southwest": {"lat": 51.5227536197085, "lng": -0.170894080291502}}}, "name": "Deborah Woolf Vintage", "place_id": "ChIJz_KwOLcadkgRs1D0J8syUxU", "types": ["jewelry_store", "point_of_interest", "clothing_store", "store", "establishment"], "rating": 4, "user_ratings_total": 4}, "ChIJ4RUgxqIPdkgRipp6dVmsBiQ": {"geometry": {"location": {"lat": 51.52422000000001, "lng": -0.1693925}, "viewport": {"northeast": {"lat": 51.5255281802915, "lng": -0.167968069708498}, "southwest": {"lat": 51.5228302197085, "lng": -0.170666030291502}}}, "name": "Dorian Caffot de Fawes Antiques", "place_id": "ChIJ4RUgxqIPdkgRipp6dVmsBiQ", "types": ["home_goods_store", "point_of_interest", "store", "establishment"], "rating": 4.8, "user_ratings_total": 5}, "ChIJAaQlR7cadkgRcbY0rGzmqc4": {"geometry": {"location": {"lat": 51.52422000000001, "lng": -0.1693925}, "viewport": {"northeast": {"lat": 51.52556898029151, "lng": -0.168043519708498}, "southwest": {"lat": 51.52287101970851, "lng": -0.170741480291502}}}, "name": "Sans Pretention", "place_id": "ChIJAaQlR7cadkgRcbY0rGzmqc4", "types": ["home_goods_store", "point_of_interest", "store", "establishment"]}, "ChIJAaQlR7cadkgRW6wWpyvuG28": {"geometry": {"location": {"lat": 51.52422000000001, "lng": -0.1693925}, "viewport": {"northeast": {"lat": 51.52556898029151, "lng": -0.168043519708498}, "southwest": {"lat": 51.52287101970851, "lng": -0.170741480291502}}}, "name": "Stephen Sprake", "place_id": "ChIJAaQlR7cadkgRW6wWpyvuG28", "types": ["home_goods_store", "point_of_interest", "store", "establishment"]}, "ChIJuy__QrcadkgRnmsTyf3qQ6Y": {"geometry": {"location": {"lat": 51.52468429999999, "lng": -0.1694148}, "viewport": {"northeast": {"lat": 51.5260144302915, "lng": -0.168088269708498}, "southwest": {"lat": 51.5233164697085, "lng": -0.170786230291502}}}, "name": "Lisson Grove Health Centre", "place_id": "ChIJuy__QrcadkgRnmsTyf3qQ6Y", "types": ["hospital", "health", "point_of_interest", "establishment"], "rating": 2.3, "user_ratings_total": 31}, "ChIJK9j9TrcadkgR2RGsHHZYtN8": {"geometry": {"location": {"lat": 51.5245562, "lng": -0.1699019}, "viewport": {"northeast": {"lat": 51.5259563302915, "lng": -0.168610619708498}, "southwest": {"lat": 51.5232583697085, "lng": -0.171308580291502}}}, "name": "Nightingale House", "place_id": "ChIJK9j9TrcadkgR2RGsHHZYtN8", "types": ["point_of_interest", "establishment"]}, "ChIJxQJsEWwPdkgRJ8yxyTlhKKw": {"geometry": {"location": {"lat": 51.52465849999999, "lng": -0.1705379}, "viewport": {"northeast": {"lat": 51.52597018029149, "lng": -0.1691165197084979}, "southwest": {"lat": 51.5232722197085, "lng": -0.171814480291502}}}, "name": "Global Kapap & Krav Maga Classes", "place_id": "ChIJxQJsEWwPdkgRJ8yxyTlhKKw", "types": ["health", "point_of_interest", "establishment"], "rating": 5, "user_ratings_total": 1}, "ChIJ__9WsrAadkgRpC0q8D_YHNs": {"geometry": {"location": {"lat": 51.524607, "lng": -0.1706411}, "viewport": {"northeast": {"lat": 51.52591338029149, "lng": -0.169209419708498}, "southwest": {"lat": 51.52321541970849, "lng": -0.171907380291502}}}, "name": "SPARKLY HOMES", "place_id": "ChIJ__9WsrAadkgRpC0q8D_YHNs", "types": ["painter", "general_contractor", "point_of_interest", "establishment"]}, "ChIJrYljKq4adkgRAayZfdvmfE0": {"geometry": {"location": {"lat": 51.5245624, "lng": -0.1696226}, "viewport": {"northeast": {"lat": 51.5259594302915, "lng": -0.168215519708498}, "southwest": {"lat": 51.5232614697085, "lng": -0.170913480291502}}}, "name": "London Dance Project", "place_id": "ChIJrYljKq4adkgRAayZfdvmfE0", "types": ["point_of_interest", "establishment"], "rating": 4.6, "user_ratings_total": 9}, "ChIJc3V5tLAadkgRU-CNcw0eyy0": {"geometry": {"location": {"lat": 51.5245659, "lng": -0.1706868}, "viewport": {"northeast": {"lat": 51.52587368029149, "lng": -0.169257769708498}, "southwest": {"lat": 51.5231757197085, "lng": -0.171955730291502}}}, "name": "Top Market Packages", "place_id": "ChIJc3V5tLAadkgRU-CNcw0eyy0", "types": ["point_of_interest", "establishment"]}, "ChIJezJpDB8bdkgRprr5DN0waws": {"geometry": {"location": {"lat": 51.5241389, "lng": -0.1705494}, "viewport": {"northeast": {"lat": 51.5254164802915, "lng": -0.169379219708498}, "southwest": {"lat": 51.5227185197085, "lng": -0.172077180291502}}}, "name": "17 Morris House", "place_id": "ChIJezJpDB8bdkgRprr5DN0waws", "types": ["university", "point_of_interest", "establishment"]}, "ChIJi3-5QbcadkgRx5Ihcd82WS4": {"geometry": {"location": {"lat": 51.5244666, "lng": -0.1694124}, "viewport": {"northeast": {"lat": 51.52587488029149, "lng": -0.168052619708498}, "southwest": {"lat": 51.5231769197085, "lng": -0.170750580291502}}}, "name": "Shtaura", "place_id": "ChIJi3-5QbcadkgRx5Ihcd82WS4", "types": ["restaurant", "food", "point_of_interest", "establishment"], "rating": 4.5, "user_ratings_total": 87}, "ChIJrxvGU7cadkgRgQR8GDghqnk": {"geometry": {"location": {"lat": 51.5249568, "lng": -0.1701141}, "viewport": {"northeast": {"lat": 51.5263057802915, "lng": -0.168765119708498}, "southwest": {"lat": 51.5236078197085, "lng": -0.171463080291502}}}, "name": "Swanbourne House", "place_id": "ChIJrxvGU7cadkgRgQR8GDghqnk", "types": ["point_of_interest", "establishment"], "rating": 4, "user_ratings_total": 1}, "ChIJMZT4N7cadkgR5dQ5sRGBcVk": {"geometry": {"location": {"lat": 51.524198, "lng": -0.1694886}, "viewport": {"northeast": {"lat": 51.5254949802915, "lng": -0.168048919708498}, "southwest": {"lat": 51.5227970197085, "lng": -0.170746880291502}}}, "name": "Bizarre", "place_id": "ChIJMZT4N7cadkgR5dQ5sRGBcVk", "types": ["home_goods_store", "point_of_interest", "store", "establishment"]}, "ChIJZaANSzAbdkgRjfXoP6HGTDg": {"geometry": {"location": {"lat": 51.52414139999999, "lng": -0.169559}, "viewport": {"northeast": {"lat": 51.52544048029149, "lng": -0.168122969708498}, "southwest": {"lat": 51.52274251970849, "lng": -0.170820930291502}}}, "name": "Bless&Tony Unisex Hair salon", "place_id": "ChIJZaANSzAbdkgRjfXoP6HGTDg", "types": ["hair_care", "health", "point_of_interest", "establishment"], "rating": 5, "user_ratings_total": 3}, "ChIJuy__QrcadkgRNOm9558cPm4": {"geometry": {"location": {"lat": 51.5244446, "lng": -0.1693522}, "viewport": {"northeast": {"lat": 51.5258387802915, "lng": -0.1679485197084979}, "southwest": {"lat": 51.5231408197085, "lng": -0.170646480291502}}}, "name": "Brown Dr Ruth", "place_id": "ChIJuy__QrcadkgRNOm9558cPm4", "types": ["doctor", "health", "point_of_interest", "establishment"]}, "ChIJuy__QrcadkgR9kYLlBFuZ20": {"geometry": {"location": {"lat": 51.5244446, "lng": -0.1693522}, "viewport": {"northeast": {"lat": 51.5258387802915, "lng": -0.1679485197084979}, "southwest": {"lat": 51.5231408197085, "lng": -0.170646480291502}}}, "name": "Mintz Dr H", "place_id": "ChIJuy__QrcadkgR9kYLlBFuZ20", "types": ["doctor", "health", "point_of_interest", "establishment"]}, "ChIJ___jarcadkgRc5PxFgbWA88": {"geometry": {"location": {"lat": 51.5241225, "lng": -0.1695837}, "viewport": {"northeast": {"lat": 51.52542208029151, "lng": -0.168148519708498}, "southwest": {"lat": 51.52272411970851, "lng": -0.170846480291502}}}, "name": "Cupio Gallery", "place_id": "ChIJ___jarcadkgRc5PxFgbWA88", "types": ["point_of_interest", "establishment"], "rating": 5, "user_ratings_total": 1}, "ChIJJTKQQ7cadkgRgF4tSrWtWhU": {"geometry": {"location": {"lat": 51.52472189999999, "lng": -0.169451}, "viewport": {"northeast": {"lat": 51.5260423302915, "lng": -0.168136519708498}, "southwest": {"lat": 51.5233443697085, "lng": -0.170834480291502}}}, "name": "Dr R H D Wormell - Lisson Grove Health Centre", "place_id": "ChIJJTKQQ7cadkgRgF4tSrWtWhU", "types": ["doctor", "health", "point_of_interest", "establishment"]}, "ChIJMWkwR7cadkgRnZ8F4RCoZug": {"geometry": {"location": {"lat": 51.52422529999999, "lng": -0.1694463}, "viewport": {"northeast": {"lat": 51.52557428029149, "lng": -0.1680973197084979}, "southwest": {"lat": 51.52287631970849, "lng": -0.170795280291502}}}, "name": "Bloch Antiques", "place_id": "ChIJMWkwR7cadkgRnZ8F4RCoZug", "types": ["home_goods_store", "point_of_interest", "store", "establishment"]}, "ChIJS0_3Q7cadkgRQFphvGCxk_s": {"geometry": {"location": {"lat": 51.5244587, "lng": -0.1693203}, "viewport": {"northeast": {"lat": 51.5258436302915, "lng": -0.167927819708498}, "southwest": {"lat": 51.52314566970851, "lng": -0.170625780291502}}}, "name": "Waste Collection St. John\u2019s Wood Ltd", "place_id": "ChIJS0_3Q7cadkgRQFphvGCxk_s", "types": ["point_of_interest", "establishment"]}, "ChIJF2pUJxUbdkgRpULNYQyIiQQ": {"geometry": {"location": {"lat": 51.5240299, "lng": -0.1697096}, "viewport": {"northeast": {"lat": 51.5253312302915, "lng": -0.1682774697084979}, "southwest": {"lat": 51.5226332697085, "lng": -0.170975430291502}}}, "name": "Dragons vape", "place_id": "ChIJF2pUJxUbdkgRpULNYQyIiQQ", "types": ["point_of_interest", "store", "establishment"]}, "ChIJK1dkGqYbdkgRqEt8n8eGKQc": {"geometry": {"location": {"lat": 51.5240299, "lng": -0.1697096}, "viewport": {"northeast": {"lat": 51.5253312302915, "lng": -0.1682774697084979}, "southwest": {"lat": 51.5226332697085, "lng": -0.170975430291502}}}, "name": "Swap shop", "place_id": "ChIJK1dkGqYbdkgRqEt8n8eGKQc", "types": ["point_of_interest", "establishment"], "rating": 5, "user_ratings_total": 3}, "ChIJA9twq0sbdkgRZQgbTLabjdI": {"geometry": {"location": {"lat": 51.5241517, "lng": -0.1694867}, "viewport": {"northeast": {"lat": 51.5254595802915, "lng": -0.168066069708498}, "southwest": {"lat": 51.5227616197085, "lng": -0.170764030291502}}}, "name": "HOOKUT", "place_id": "ChIJA9twq0sbdkgRZQgbTLabjdI", "types": ["hair_care", "health", "point_of_interest", "establishment"], "rating": 5, "user_ratings_total": 7}, "ChIJRUZgM7cadkgRlDp7v91ejGg": {"geometry": {"location": {"lat": 51.523754, "lng": -0.1703513}, "viewport": {"northeast": {"lat": 51.5251029802915, "lng": -0.169002319708498}, "southwest": {"lat": 51.5224050197085, "lng": -0.1717002802915021}}}, "name": "Red Bus Studios Ltd", "place_id": "ChIJRUZgM7cadkgRlDp7v91ejGg", "types": ["electronics_store", "home_goods_store", "point_of_interest", "store", "establishment"], "rating": 4.3, "user_ratings_total": 3}, "ChIJjxNUMbcadkgR6Hs7JgWgh_o": {"geometry": {"location": {"lat": 51.5237541, "lng": -0.1700784}, "viewport": {"northeast": {"lat": 51.52510308029149, "lng": -0.168729419708498}, "southwest": {"lat": 51.52240511970849, "lng": -0.1714273802915021}}}, "name": "Snipping Image Hairdressing", "place_id": "ChIJjxNUMbcadkgR6Hs7JgWgh_o", "types": ["hair_care", "point_of_interest", "establishment"], "rating": 4.3, "user_ratings_total": 12}, "ChIJRUZgM7cadkgRWiOB_qNbVfE": {"geometry": {"location": {"lat": 51.523754, "lng": -0.1703513}, "viewport": {"northeast": {"lat": 51.5250930302915, "lng": -0.1690129697084979}, "southwest": {"lat": 51.5223950697085, "lng": -0.171710930291502}}}, "name": "Hantarex International Ltd", "place_id": "ChIJRUZgM7cadkgRWiOB_qNbVfE", "types": ["point_of_interest", "establishment"]}, "ChIJCzv-NrcadkgRQelPmwfoEuM": {"geometry": {"location": {"lat": 51.52390639999999, "lng": -0.1698929}, "viewport": {"northeast": {"lat": 51.52520763029149, "lng": -0.168460669708498}, "southwest": {"lat": 51.5225096697085, "lng": -0.171158630291502}}}, "name": "Patricia Harvey Antiques", "place_id": "ChIJCzv-NrcadkgRQelPmwfoEuM", "types": ["furniture_store", "home_goods_store", "point_of_interest", "store", "establishment"]}, "ChIJ-bbAwHkRdkgRGMsjDRbsEbE": {"geometry": {"location": {"lat": 51.5239059, "lng": -0.169858}, "viewport": {"northeast": {"lat": 51.5252166802915, "lng": -0.168429469708498}, "southwest": {"lat": 51.52251871970851, "lng": -0.171127430291502}}}, "name": "Les Trois Gar\u00e7ons", "place_id": "ChIJ-bbAwHkRdkgRGMsjDRbsEbE", "types": ["furniture_store", "home_goods_store", "restaurant", "food", "point_of_interest", "store", "establishment"], "rating": 4, "user_ratings_total": 38}, "ChIJc8vbNrcadkgRdkWqQ1OFZsw": {"geometry": {"location": {"lat": 51.52379750000001, "lng": -0.1700246}, "viewport": {"northeast": {"lat": 51.52514648029151, "lng": -0.168675619708498}, "southwest": {"lat": 51.52244851970851, "lng": -0.171373580291502}}}, "name": "Home | Lamia Hair and Beauty Salon", "place_id": "ChIJc8vbNrcadkgRdkWqQ1OFZsw", "types": ["beauty_salon", "point_of_interest", "establishment"], "rating": 3.5, "user_ratings_total": 53}, "ChIJF9VZMbcadkgRb4puqOTVG-8": {"geometry": {"location": {"lat": 51.5236957, "lng": -0.1701477}, "viewport": {"northeast": {"lat": 51.5250065802915, "lng": -0.168729919708498}, "southwest": {"lat": 51.5223086197085, "lng": -0.171427880291502}}}, "name": "The Trader's Inn", "place_id": "ChIJF9VZMbcadkgRb4puqOTVG-8", "types": ["bar", "point_of_interest", "establishment"], "rating": 4.3, "user_ratings_total": 61}, "ChIJDVQyP7cadkgR-Tw-jS-82aM": {"geometry": {"location": {"lat": 51.5236578, "lng": -0.1697676}, "viewport": {"northeast": {"lat": 51.52500678029151, "lng": -0.168418619708498}, "southwest": {"lat": 51.52230881970851, "lng": -0.1711165802915021}}}, "name": "Vassos Shoe Repairs", "place_id": "ChIJDVQyP7cadkgR-Tw-jS-82aM", "types": ["point_of_interest", "establishment"], "rating": 4.2, "user_ratings_total": 5}, "ChIJJXpMMbcadkgR6RvUpjX0myk": {"geometry": {"location": {"lat": 51.5237433, "lng": -0.1700049}, "viewport": {"northeast": {"lat": 51.5250646302915, "lng": -0.168607719708498}, "southwest": {"lat": 51.5223666697085, "lng": -0.171305680291502}}}, "name": "The Motherkutter Kult Klub", "place_id": "ChIJJXpMMbcadkgR6RvUpjX0myk", "types": ["point_of_interest", "establishment"]}, "ChIJVQaRKcMbdkgRbr_EGpSgnoM": {"geometry": {"location": {"lat": 51.5237441, "lng": -0.1700054}, "viewport": {"northeast": {"lat": 51.5250653302915, "lng": -0.168607569708498}, "southwest": {"lat": 51.5223673697085, "lng": -0.1713055302915021}}}, "name": "Lynks London", "place_id": "ChIJVQaRKcMbdkgRbr_EGpSgnoM", "types": ["point_of_interest", "establishment"], "rating": 5, "user_ratings_total": 5}, "ChIJ_VS1fuUbdkgRHLz4IGf7zH8": {"geometry": {"location": {"lat": 51.5236684, "lng": -0.1696846}, "viewport": {"northeast": {"lat": 51.5250565802915, "lng": -0.1684040197084979}, "southwest": {"lat": 51.5223586197085, "lng": -0.171101980291502}}}, "name": "Westminster Wheels", "place_id": "ChIJ_VS1fuUbdkgRHLz4IGf7zH8", "types": ["point_of_interest", "establishment"], "rating": 5, "user_ratings_total": 5}, "ChIJCzD8MrcadkgR6uWoRbdVVDE": {"geometry": {"location": {"lat": 51.5236665, "lng": -0.1706035}, "viewport": {"northeast": {"lat": 51.52504888029149, "lng": -0.169208469708498}, "southwest": {"lat": 51.5223509197085, "lng": -0.171906430291502}}}, "name": "Love Venezia", "place_id": "ChIJCzD8MrcadkgR6uWoRbdVVDE", "types": ["cafe", "food", "point_of_interest", "establishment"], "rating": 4, "user_ratings_total": 1}, "ChIJ89FwD9UEdkgRB66fVLazQuI": {"geometry": {"location": {"lat": 51.523832, "lng": -0.169945}, "viewport": {"northeast": {"lat": 51.5251684302915, "lng": -0.168520719708498}, "southwest": {"lat": 51.5224704697085, "lng": -0.171218680291502}}}, "name": "Mr Ducktail", "place_id": "ChIJ89FwD9UEdkgRB66fVLazQuI", "types": ["hair_care", "health", "point_of_interest", "clothing_store", "store", "establishment"], "rating": 4.7, "user_ratings_total": 16}, "ChIJvzGdZukbdkgRpPzxZ9miBi8": {"geometry": {"location": {"lat": 51.5238627, "lng": -0.1701806}, "viewport": {"northeast": {"lat": 51.5251293802915, "lng": -0.168688119708498}, "southwest": {"lat": 51.5224314197085, "lng": -0.171386080291502}}}, "name": "Shisha Delivery West London", "place_id": "ChIJvzGdZukbdkgRpPzxZ9miBi8", "types": ["doctor", "health", "point_of_interest", "establishment"]}, "ChIJTRH2oO4edkgR86i8cW5Dco0": {"geometry": {"location": {"lat": 51.5236707, "lng": -0.1707432}, "viewport": {"northeast": {"lat": 51.52489093029151, "lng": -0.169179969708498}, "southwest": {"lat": 51.52219296970851, "lng": -0.171877930291502}}}, "name": "love venezia caf\u00e9", "place_id": "ChIJTRH2oO4edkgR86i8cW5Dco0", "types": ["cafe", "restaurant", "food", "point_of_interest", "establishment"], "rating": 5, "user_ratings_total": 1}, "ChIJ50gxMbcadkgRiGOrEnxWoqk": {"geometry": {"location": {"lat": 51.5238996, "lng": -0.1699123}, "viewport": {"northeast": {"lat": 51.5251994302915, "lng": -0.168477569708498}, "southwest": {"lat": 51.52250146970851, "lng": -0.171175530291502}}}, "name": "Church Street Crepes", "place_id": "ChIJ50gxMbcadkgRiGOrEnxWoqk", "types": ["meal_takeaway", "restaurant", "food", "point_of_interest", "establishment"]}, "ChIJ__8LLjAfdkgRILhF4LeuqTg": {"geometry": {"location": {"lat": 51.523793, "lng": -0.1695646}, "viewport": {"northeast": {"lat": 51.5251711802915, "lng": -0.168266569708498}, "southwest": {"lat": 51.5224732197085, "lng": -0.170964530291502}}}, "name": "Adensat", "place_id": "ChIJ__8LLjAfdkgRILhF4LeuqTg", "types": ["store", "point_of_interest", "establishment"]}, "ChIJmZdzObcadkgRD32fJTVtNb8": {"geometry": {"location": {"lat": 51.5237931, "lng": -0.1695646}, "viewport": {"northeast": {"lat": 51.5251420802915, "lng": -0.1682156197084979}, "southwest": {"lat": 51.5224441197085, "lng": -0.1709135802915019}}}, "name": "Cali Cafe", "place_id": "ChIJmZdzObcadkgRD32fJTVtNb8", "types": ["cafe", "food", "point_of_interest", "establishment"], "rating": 4.7, "user_ratings_total": 55}, "ChIJWRMIa7oadkgR3qGKJQx59Wo": {"geometry": {"location": {"lat": 51.5264926838774, "lng": -0.1720534685682216}, "viewport": {"northeast": {"lat": 51.52784168029149, "lng": -0.170704469708498}, "southwest": {"lat": 51.5251437197085, "lng": -0.173402430291502}}}, "name": "219 B507", "place_id": "ChIJWRMIa7oadkgR3qGKJQx59Wo", "types": ["route"]}, "ChIJP_PtEboadkgR1-_sVWVIh2o": {"geometry": {"location": {"lat": 51.5263146, "lng": -0.1719742}, "viewport": {"northeast": {"lat": 51.52770993029149, "lng": -0.170601519708498}, "southwest": {"lat": 51.52501196970849, "lng": -0.1732994802915021}}}, "name": "Westminster Learning Disability Partnership", "place_id": "ChIJP_PtEboadkgR1-_sVWVIh2o", "types": ["hospital", "health", "point_of_interest", "establishment"]}, "ChIJP1iibLoadkgRvHwd2jtlliY": {"geometry": {"location": {"lat": 51.52633110000001, "lng": -0.1719986}, "viewport": {"northeast": {"lat": 51.5277365302915, "lng": -0.170641919708498}, "southwest": {"lat": 51.5250385697085, "lng": -0.173339880291502}}}, "name": "Westminster Adult Education Service", "place_id": "ChIJP1iibLoadkgRvHwd2jtlliY", "types": ["university", "school", "point_of_interest", "establishment"], "rating": 3.8, "user_ratings_total": 58}, "ChIJhUKUa7oadkgR84XmxAnRJVs": {"geometry": {"location": {"lat": 51.52644799999999, "lng": -0.17219}, "viewport": {"northeast": {"lat": 51.52779698029149, "lng": -0.170841019708498}, "southwest": {"lat": 51.5250990197085, "lng": -0.1735389802915021}}}, "name": "Santander Cycles", "place_id": "ChIJhUKUa7oadkgR84XmxAnRJVs", "types": ["point_of_interest", "establishment"]}, "ChIJQU6ZbLoadkgRRncuN8z9MqE": {"geometry": {"location": {"lat": 51.5263592, "lng": -0.1720401}, "viewport": {"northeast": {"lat": 51.5277497302915, "lng": -0.170642369708498}, "southwest": {"lat": 51.5250517697085, "lng": -0.173340330291502}}}, "name": "Ecole", "place_id": "ChIJQU6ZbLoadkgRRncuN8z9MqE", "types": ["school", "point_of_interest", "establishment"]}, "ChIJ2948EroadkgRssdlNc9eEOo": {"geometry": {"location": {"lat": 51.5261466, "lng": -0.1716096}, "viewport": {"northeast": {"lat": 51.52754413029151, "lng": -0.170204619708498}, "southwest": {"lat": 51.52484616970851, "lng": -0.172902580291502}}}, "name": "Westminster Youth Council & Participation", "place_id": "ChIJ2948EroadkgRssdlNc9eEOo", "types": ["point_of_interest", "establishment"]}, "ChIJU3OUEroadkgRpe_YQHOq12I": {"geometry": {"location": {"lat": 51.5261199, "lng": -0.1718135}, "viewport": {"northeast": {"lat": 51.5275581802915, "lng": -0.170322119708498}, "southwest": {"lat": 51.5248602197085, "lng": -0.173020080291502}}}, "name": "Westminster Duke of Edinburgh's Awards", "place_id": "ChIJU3OUEroadkgRpe_YQHOq12I", "types": ["point_of_interest", "establishment"], "rating": 5, "user_ratings_total": 1}, "ChIJhefenbAadkgRRrnruC5wRaY": {"geometry": {"location": {"lat": 51.52533146184319, "lng": -0.1722628454089832}, "viewport": {"northeast": {"lat": 51.52668078029149, "lng": -0.170914619708498}, "southwest": {"lat": 51.52398281970849, "lng": -0.1736125802915021}}}, "name": "28-8 Frampton St", "place_id": "ChIJhefenbAadkgRRrnruC5wRaY", "types": ["route"]}, "ChIJ34tHbLoadkgRrjxwua18W5k": {"geometry": {"location": {"lat": 51.5254653, "lng": -0.1719305}, "viewport": {"northeast": {"lat": 51.5268402302915, "lng": -0.1706385697084979}, "southwest": {"lat": 51.5241422697085, "lng": -0.173336530291502}}}, "name": "Family Information Service", "place_id": "ChIJ34tHbLoadkgRrjxwua18W5k", "types": ["point_of_interest", "establishment"]}, "ChIJbT4KDroadkgRg8AWJ3o8et4": {"geometry": {"location": {"lat": 51.5254653, "lng": -0.1719305}, "viewport": {"northeast": {"lat": 51.5268402302915, "lng": -0.1706385697084979}, "southwest": {"lat": 51.5241422697085, "lng": -0.173336530291502}}}, "name": "Housing 21 Care Services", "place_id": "ChIJbT4KDroadkgRg8AWJ3o8et4", "types": ["point_of_interest", "establishment"], "rating": 5, "user_ratings_total": 1}, "ChIJg6hzDLoadkgRtclUNxcrza0": {"geometry": {"location": {"lat": 51.5253865, "lng": -0.1719908}, "viewport": {"northeast": {"lat": 51.52676623029149, "lng": -0.170709369708498}, "southwest": {"lat": 51.5240682697085, "lng": -0.173407330291502}}}, "name": "Zipcar UK - Frampton St E", "place_id": "ChIJg6hzDLoadkgRtclUNxcrza0", "types": ["point_of_interest", "establishment"], "rating": 1, "user_ratings_total": 1}, "ChIJbRpLdboadkgR3h37FO0NUX4": {"geometry": {"location": {"lat": 51.5260458, "lng": -0.1717999}, "viewport": {"northeast": {"lat": 51.52727563029151, "lng": -0.170405319708498}, "southwest": {"lat": 51.52457766970851, "lng": -0.173103280291502}}}, "name": "Westminster City Council", "place_id": "ChIJbRpLdboadkgR3h37FO0NUX4", "types": ["point_of_interest", "establishment"], "rating": 2, "user_ratings_total": 8}, "ChIJq9g4bLoadkgRrcF0eVuKAEs": {"geometry": {"location": {"lat": 51.526045, "lng": -0.1720395}, "viewport": {"northeast": {"lat": 51.5273236802915, "lng": -0.170810169708498}, "southwest": {"lat": 51.5246257197085, "lng": -0.173508130291502}}}, "name": "Westminster Information Advice Support Service (IASS) for SEND", "place_id": "ChIJq9g4bLoadkgRrcF0eVuKAEs", "types": ["point_of_interest", "establishment"], "rating": 3, "user_ratings_total": 2}, "ChIJbT4KDroadkgRasBvq5IdqO4": {"geometry": {"location": {"lat": 51.5254653, "lng": -0.1719305}, "viewport": {"northeast": {"lat": 51.5268402302915, "lng": -0.1706385697084979}, "southwest": {"lat": 51.5241422697085, "lng": -0.173336530291502}}}, "name": "Family Recovery Project", "place_id": "ChIJbT4KDroadkgRasBvq5IdqO4", "types": ["point_of_interest", "establishment"], "rating": 5, "user_ratings_total": 1}, "ChIJPXi_CboadkgR95vpRShAb7A": {"geometry": {"location": {"lat": 51.52548099999999, "lng": -0.171451}, "viewport": {"northeast": {"lat": 51.52682883029149, "lng": -0.170103519708498}, "southwest": {"lat": 51.52413086970849, "lng": -0.172801480291502}}}, "name": "ubitricity Charging Station", "place_id": "ChIJPXi_CboadkgR95vpRShAb7A", "types": ["point_of_interest", "establishment"]}, "ChIJYZBZnbAadkgRI9Yh9NdmVRE": {"geometry": {"location": {"lat": 51.5255222, "lng": -0.1724615}, "viewport": {"northeast": {"lat": 51.52680853029149, "lng": -0.170974769708498}, "southwest": {"lat": 51.52411056970849, "lng": -0.173672730291502}}}, "name": "Aramic Interiors", "place_id": "ChIJYZBZnbAadkgRI9Yh9NdmVRE", "types": ["general_contractor", "point_of_interest", "establishment"]}, "ChIJdRUBV7cadkgRr6peTq8PZv8": {"geometry": {"location": {"lat": 51.5256844, "lng": -0.1711422}, "viewport": {"northeast": {"lat": 51.5269342302915, "lng": -0.169913019708498}, "southwest": {"lat": 51.5242362697085, "lng": -0.172610980291502}}}, "name": "Shojujitsu Karate Do Association", "place_id": "ChIJdRUBV7cadkgRr6peTq8PZv8", "types": ["health", "point_of_interest", "establishment"], "rating": 5, "user_ratings_total": 1}, "ChIJcYfHkLAadkgRbzJDdjybKa0": {"geometry": {"location": {"lat": 51.52456406185383, "lng": -0.172120739924898}, "viewport": {"northeast": {"lat": 51.52591198029149, "lng": -0.1707733197084979}, "southwest": {"lat": 51.52321401970849, "lng": -0.173471280291502}}}, "name": "25-17 Fisherton St", "place_id": "ChIJcYfHkLAadkgRbzJDdjybKa0", "types": ["route"]}, "ChIJi1PjlbAadkgRoCUtNbeWrCY": {"geometry": {"location": {"lat": 51.52443639999999, "lng": -0.1721016}, "viewport": {"northeast": {"lat": 51.5257553302915, "lng": -0.170693119708498}, "southwest": {"lat": 51.5230573697085, "lng": -0.173391080291502}}}, "name": "St Pauls Newpin", "place_id": "ChIJi1PjlbAadkgRoCUtNbeWrCY", "types": ["point_of_interest", "establishment"], "rating": 4, "user_ratings_total": 1}, "ChIJWa0bmLAadkgRMPtmW8xNLZ0": {"geometry": {"location": {"lat": 51.52476919999999, "lng": -0.1719789}, "viewport": {"northeast": {"lat": 51.52603578029149, "lng": -0.170741219708498}, "southwest": {"lat": 51.52333781970849, "lng": -0.173439180291502}}}, "name": "Hasim Vitija Memorial Bench", "place_id": "ChIJWa0bmLAadkgRMPtmW8xNLZ0", "types": ["point_of_interest", "establishment"], "rating": 4.3, "user_ratings_total": 7}, "ChIJaX3hjbAadkgRjf3gbBKAS9c": {"geometry": {"location": {"lat": 51.524611, "lng": -0.1726359}, "viewport": {"northeast": {"lat": 51.52603053029151, "lng": -0.171441269708498}, "southwest": {"lat": 51.52333256970851, "lng": -0.174139230291502}}}, "name": "Eastlake House", "place_id": "ChIJaX3hjbAadkgRjf3gbBKAS9c", "types": ["point_of_interest", "establishment"], "rating": 4.3, "user_ratings_total": 6}, "ChIJ1-X5r7AadkgR9O1MruTv1ZY": {"geometry": {"location": {"lat": 51.5248014, "lng": -0.1711138}, "viewport": {"northeast": {"lat": 51.52612780730449, "lng": -0.1698149308278273}, "southwest": {"lat": 51.5234298467215, "lng": -0.1725128914108313}}}, "name": "Parking lot", "place_id": "ChIJ1-X5r7AadkgR9O1MruTv1ZY", "types": ["parking", "premise", "point_of_interest", "establishment"]}, "ChIJgWqJuLAadkgR2ioDhKQSp7U": {"geometry": {"location": {"lat": 51.5241439, "lng": -0.1713857}, "viewport": {"northeast": {"lat": 51.52549193801622, "lng": -0.1700333999981951}, "southwest": {"lat": 51.52279397743322, "lng": -0.1727313605811991}}}, "name": "Parking lot", "place_id": "ChIJgWqJuLAadkgR2ioDhKQSp7U", "types": ["parking", "premise", "point_of_interest", "establishment"]}, "ChIJ5TEgf7cadkgRIKMV_NRqPoE": {"geometry": {"location": {"lat": 51.5252562, "lng": -0.1676154}, "viewport": {"northeast": {"lat": 51.5266488302915, "lng": -0.166116519708498}, "southwest": {"lat": 51.5239508697085, "lng": -0.168814480291502}}}, "name": "Green Laundrette & Dry Cleaning", "place_id": "ChIJ5TEgf7cadkgRIKMV_NRqPoE", "types": ["laundry", "point_of_interest", "establishment"], "rating": 4.7, "user_ratings_total": 40}, "ChIJpZZwDP0bdkgRTiwXDN1f3qM": {"geometry": {"location": {"lat": 51.52516180000001, "lng": -0.1675696}, "viewport": {"northeast": {"lat": 51.52651078029151, "lng": -0.166220619708498}, "southwest": {"lat": 51.52381281970851, "lng": -0.168918580291502}}}, "name": "Cheap Virtual Office", "place_id": "ChIJpZZwDP0bdkgRTiwXDN1f3qM", "types": ["point_of_interest", "establishment"], "rating": 4.9, "user_ratings_total": 43}, "ChIJraz_hrcadkgRVXfipNoW1x0": {"geometry": {"location": {"lat": 51.52518169999999, "lng": -0.1677234}, "viewport": {"northeast": {"lat": 51.52651273029149, "lng": -0.166321869708498}, "southwest": {"lat": 51.52381476970849, "lng": -0.169019830291502}}}, "name": "ATM (Local Minimarket)", "place_id": "ChIJraz_hrcadkgRVXfipNoW1x0", "types": ["atm", "finance", "point_of_interest", "establishment"]}, "ChIJi4G4RQkbdkgRrYqIVuvYfFU": {"geometry": {"location": {"lat": 51.52520800000001, "lng": -0.1676368}, "viewport": {"northeast": {"lat": 51.5265326302915, "lng": -0.166258019708498}, "southwest": {"lat": 51.5238346697085, "lng": -0.168955980291502}}}, "name": "Local Mini Market", "place_id": "ChIJi4G4RQkbdkgRrYqIVuvYfFU", "types": ["liquor_store", "point_of_interest", "store", "establishment"], "rating": 3.4, "user_ratings_total": 5}, "ChIJ9-NGt5kbdkgRN2Fl2lA9iDI": {"geometry": {"location": {"lat": 51.5252074, "lng": -0.1677224}, "viewport": {"northeast": {"lat": 51.5265190302915, "lng": -0.166327669708498}, "southwest": {"lat": 51.5238210697085, "lng": -0.169025630291502}}}, "name": "Wakeflow Ltd.", "place_id": "ChIJ9-NGt5kbdkgRN2Fl2lA9iDI", "types": ["point_of_interest", "establishment"]}, "ChIJcRvQtwIbdkgRGtCbjhUxpM0": {"geometry": {"location": {"lat": 51.5252074, "lng": -0.1677224}, "viewport": {"northeast": {"lat": 51.5265190302915, "lng": -0.166327669708498}, "southwest": {"lat": 51.5238210697085, "lng": -0.169025630291502}}}, "name": "Global Nostalgia", "place_id": "ChIJcRvQtwIbdkgRGtCbjhUxpM0", "types": ["point_of_interest", "store", "establishment"]}, "ChIJeZC9DugZdkgR2RzYflGxAn0": {"geometry": {"location": {"lat": 51.5252562, "lng": -0.1676154}, "viewport": {"northeast": {"lat": 51.5265706302915, "lng": -0.166219469708498}, "southwest": {"lat": 51.5238726697085, "lng": -0.168917430291502}}}, "name": "Timeline Business Solutions", "place_id": "ChIJeZC9DugZdkgR2RzYflGxAn0", "types": ["finance", "point_of_interest", "establishment"]}, "ChIJPeL9nh1ydkgRDLtURGCDGUc": {"geometry": {"location": {"lat": 51.52528820000001, "lng": -0.1675565}, "viewport": {"northeast": {"lat": 51.52660233029151, "lng": -0.166160169708498}, "southwest": {"lat": 51.52390436970851, "lng": -0.168858130291502}}}, "name": "Reyassoc UK Ltd", "place_id": "ChIJPeL9nh1ydkgRDLtURGCDGUc", "types": ["point_of_interest", "establishment"]}, "ChIJAZi0dbcadkgR-PT6GNyIkL8": {"geometry": {"location": {"lat": 51.52431600047476, "lng": -0.1676781981064504}, "viewport": {"northeast": {"lat": 51.5256649802915, "lng": -0.166329219708498}, "southwest": {"lat": 51.5229670197085, "lng": -0.169027180291502}}}, "name": "118 B507", "place_id": "ChIJAZi0dbcadkgR-PT6GNyIkL8", "types": ["route"]}, "ChIJVVXKdLcadkgR4jA8WGccV30": {"geometry": {"location": {"lat": 51.5240978, "lng": -0.1677632}, "viewport": {"northeast": {"lat": 51.5255026802915, "lng": -0.166302769708498}, "southwest": {"lat": 51.5228047197085, "lng": -0.169000730291502}}}, "name": "Fruitstoyou", "place_id": "ChIJVVXKdLcadkgR4jA8WGccV30", "types": ["food", "point_of_interest", "store", "establishment"], "rating": 4, "user_ratings_total": 1}, "ChIJISzTdbcadkgRyvCPf7dBHts": {"geometry": {"location": {"lat": 51.5244192, "lng": -0.1676761}, "viewport": {"northeast": {"lat": 51.52574578029149, "lng": -0.166366019708498}, "southwest": {"lat": 51.52304781970849, "lng": -0.169063980291502}}}, "name": "Church Street Market Lisson Grove (Stop LJ)", "place_id": "ChIJISzTdbcadkgRyvCPf7dBHts", "types": ["bus_station", "transit_station", "point_of_interest", "establishment"], "rating": 3.5, "user_ratings_total": 2}, "ChIJEe2f3bkadkgRbVVX4ecLlmQ": {"geometry": {"location": {"lat": 51.52590587524409, "lng": -0.1689124218491386}, "viewport": {"northeast": {"lat": 51.5272383302915, "lng": -0.167527119708498}, "southwest": {"lat": 51.5245403697085, "lng": -0.170225080291502}}}, "name": "11-25 Bernhardt Cres", "place_id": "ChIJEe2f3bkadkgRbVVX4ecLlmQ", "types": ["route"]}, "ChIJV54C6bkadkgRh_t7_mrIePM": {"geometry": {"location": {"lat": 51.52622179999999, "lng": -0.1692068}, "viewport": {"northeast": {"lat": 51.5276302802915, "lng": -0.167934419708498}, "southwest": {"lat": 51.5249323197085, "lng": -0.170632380291502}}}, "name": "London Accommodation", "place_id": "ChIJV54C6bkadkgRh_t7_mrIePM", "types": ["lodging", "point_of_interest", "establishment"], "rating": 5, "user_ratings_total": 3}, "ChIJFTqecTYbdkgRsD8sJPOUg-I": {"geometry": {"location": {"lat": 51.52591109999999, "lng": -0.1690916}, "viewport": {"northeast": {"lat": 51.5272310302915, "lng": -0.167702519708498}, "southwest": {"lat": 51.5245330697085, "lng": -0.170400480291502}}}, "name": "pro maintenance 247", "place_id": "ChIJFTqecTYbdkgRsD8sJPOUg-I", "types": ["point_of_interest", "establishment"]}, "ChIJTSplANcbdkgRmd3Blmc1OBI": {"geometry": {"location": {"lat": 51.52591109999999, "lng": -0.1690916}, "viewport": {"northeast": {"lat": 51.5272310302915, "lng": -0.167702519708498}, "southwest": {"lat": 51.5245330697085, "lng": -0.170400480291502}}}, "name": "emergency electricians 247", "place_id": "ChIJTSplANcbdkgRmd3Blmc1OBI", "types": ["electrician", "point_of_interest", "establishment"], "rating": 5, "user_ratings_total": 1}, "ChIJSYEbuIMbdkgRneCnCiPLcko": {"geometry": {"location": {"lat": 51.526427, "lng": -0.1693073}, "viewport": {"northeast": {"lat": 51.5277640802915, "lng": -0.167942969708498}, "southwest": {"lat": 51.5250661197085, "lng": -0.170640930291502}}}, "name": "Maryam", "place_id": "ChIJSYEbuIMbdkgRneCnCiPLcko", "types": ["night_club", "point_of_interest", "establishment"]}, "ChIJJTKQQ7cadkgRReCIjwOGBEI": {"geometry": {"location": {"lat": 51.524745, "lng": -0.169356}, "viewport": {"northeast": {"lat": 51.5260438802915, "lng": -0.168067619708498}, "southwest": {"lat": 51.5233459197085, "lng": -0.170765580291502}}}, "name": "Lisson Grove Orthodontics Clinic", "place_id": "ChIJJTKQQ7cadkgRReCIjwOGBEI", "types": ["hospital", "health", "point_of_interest", "establishment"]}, "ChIJz-sua-cbdkgRdG5wdgPwtsg": {"geometry": {"location": {"lat": 51.5250486, "lng": -0.1693557}, "viewport": {"northeast": {"lat": 51.5264647802915, "lng": -0.167925969708498}, "southwest": {"lat": 51.5237668197085, "lng": -0.170623930291502}}}, "name": "Property Accountant Lisson Grove", "place_id": "ChIJz-sua-cbdkgRdG5wdgPwtsg", "types": ["accounting", "finance", "point_of_interest", "establishment"]}, "ChIJy4CDECcbdkgRd996Fd5Q5jc": {"geometry": {"location": {"lat": 51.5249158, "lng": -0.1692883}, "viewport": {"northeast": {"lat": 51.52636448029149, "lng": -0.167819469708498}, "southwest": {"lat": 51.52366651970849, "lng": -0.170517430291502}}}, "name": "Mobile Tyre Fitters Near Lisson Grove", "place_id": "ChIJy4CDECcbdkgRd996Fd5Q5jc", "types": ["car_repair", "point_of_interest", "store", "establishment"]}, "ChIJM45o2RkbdkgRTIVOocmXUSw": {"geometry": {"location": {"lat": 51.52503769999999, "lng": -0.1689597}, "viewport": {"northeast": {"lat": 51.5263851802915, "lng": -0.167612569708498}, "southwest": {"lat": 51.5236872197085, "lng": -0.170310530291502}}}, "name": "Akhi Garms", "place_id": "ChIJM45o2RkbdkgRTIVOocmXUSw", "types": ["clothing_store", "point_of_interest", "store", "establishment"]}, "ChIJMVcjpQUbdkgRta0PLgD56OA": {"geometry": {"location": {"lat": 51.52457, "lng": -0.169129}, "viewport": {"northeast": {"lat": 51.52583343029149, "lng": -0.167644719708498}, "southwest": {"lat": 51.52313546970849, "lng": -0.170342680291502}}}, "name": "Lahori Church Street", "place_id": "ChIJMVcjpQUbdkgRta0PLgD56OA", "types": ["restaurant", "food", "point_of_interest", "establishment"], "rating": 4.2, "user_ratings_total": 56}, "ChIJcatCQrcadkgRssz3QgS9eiY": {"geometry": {"location": {"lat": 51.52457, "lng": -0.1691289}, "viewport": {"northeast": {"lat": 51.5258334802915, "lng": -0.167644619708498}, "southwest": {"lat": 51.5231355197085, "lng": -0.170342580291502}}}, "name": "In Motion Media Group", "place_id": "ChIJcatCQrcadkgRssz3QgS9eiY", "types": ["point_of_interest", "establishment"]}, "ChIJU4R4P7cadkgR_A30NcFGaSQ": {"geometry": {"location": {"lat": 51.52405585006009, "lng": -0.1691251997891513}, "viewport": {"northeast": {"lat": 51.52540483029151, "lng": -0.167776219708498}, "southwest": {"lat": 51.52270686970851, "lng": -0.170474180291502}}}, "name": "Ashbridge Street", "place_id": "ChIJU4R4P7cadkgR_A30NcFGaSQ", "types": ["route"]}, "ChIJqbxNFbcadkgREFtLvPD4fvU": {"geometry": {"location": {"lat": 51.5240017, "lng": -0.1689054}, "viewport": {"northeast": {"lat": 51.5254956802915, "lng": -0.167668269708498}, "southwest": {"lat": 51.5227977197085, "lng": -0.170366230291502}}}, "name": "Dodo", "place_id": "ChIJqbxNFbcadkgREFtLvPD4fvU", "types": ["home_goods_store", "point_of_interest", "store", "establishment"]}, "ChIJqbxNFbcadkgRjaP_o8JapTM": {"geometry": {"location": {"lat": 51.5241287, "lng": -0.1690963}, "viewport": {"northeast": {"lat": 51.52545563029151, "lng": -0.167763669708498}, "southwest": {"lat": 51.52275766970851, "lng": -0.170461630291502}}}, "name": "Tin Tin Collectables", "place_id": "ChIJqbxNFbcadkgRjaP_o8JapTM", "types": ["home_goods_store", "point_of_interest", "store", "establishment"], "rating": 5, "user_ratings_total": 1}, "ChIJqbxNFbcadkgRJGFh_l2ssY4": {"geometry": {"location": {"lat": 51.5240247, "lng": -0.1688729}, "viewport": {"northeast": {"lat": 51.5255020802915, "lng": -0.167666619708498}, "southwest": {"lat": 51.5228041197085, "lng": -0.1703645802915021}}}, "name": "THIRTEEN INTERIORS", "place_id": "ChIJqbxNFbcadkgRJGFh_l2ssY4", "types": ["furniture_store", "home_goods_store", "point_of_interest", "store", "establishment"], "rating": 4.7, "user_ratings_total": 7}, "ChIJMZT4N7cadkgRxTgRxQITNuI": {"geometry": {"location": {"lat": 51.52428649999999, "lng": -0.1692935}, "viewport": {"northeast": {"lat": 51.52563548029149, "lng": -0.167944519708498}, "southwest": {"lat": 51.52293751970849, "lng": -0.170642480291502}}}, "name": "Schmid McDonagh", "place_id": "ChIJMZT4N7cadkgRxTgRxQITNuI", "types": ["home_goods_store", "point_of_interest", "store", "establishment"], "rating": 4, "user_ratings_total": 2}, "ChIJt_HvOLcadkgRLs2kBFjQ164": {"geometry": {"location": {"lat": 51.5239437, "lng": -0.1697594}, "viewport": {"northeast": {"lat": 51.5252520302915, "lng": -0.168355869708498}, "southwest": {"lat": 51.52255406970851, "lng": -0.171053830291502}}}, "name": "The FM Gallery", "place_id": "ChIJt_HvOLcadkgRLs2kBFjQ164", "types": ["jewelry_store", "furniture_store", "home_goods_store", "general_contractor", "point_of_interest", "store", "establishment"], "rating": 5, "user_ratings_total": 3}, "ChIJe6qDOLcadkgR5jS73lAO--A": {"geometry": {"location": {"lat": 51.5239775, "lng": -0.1693187}, "viewport": {"northeast": {"lat": 51.5253264802915, "lng": -0.167969719708498}, "southwest": {"lat": 51.5226285197085, "lng": -0.170667680291502}}}, "name": "VINCENZO CAFFARELLA", "place_id": "ChIJe6qDOLcadkgR5jS73lAO--A", "types": ["art_gallery", "home_goods_store", "point_of_interest", "store", "establishment"], "rating": 5, "user_ratings_total": 1}, "ChIJuWHWPrcadkgRIsgXpPlp4rc": {"geometry": {"location": {"lat": 51.5239111, "lng": -0.1693096}, "viewport": {"northeast": {"lat": 51.5253016802915, "lng": -0.168033219708498}, "southwest": {"lat": 51.5226037197085, "lng": -0.1707311802915021}}}, "name": "Maison", "place_id": "ChIJuWHWPrcadkgRIsgXpPlp4rc", "types": ["home_goods_store", "point_of_interest", "store", "establishment"]}, "ChIJuWHWPrcadkgRuDyueXlibyE": {"geometry": {"location": {"lat": 51.5239111, "lng": -0.1693096}, "viewport": {"northeast": {"lat": 51.5253016802915, "lng": -0.168033219708498}, "southwest": {"lat": 51.5226037197085, "lng": -0.1707311802915021}}}, "name": "Focus Inside", "place_id": "ChIJuWHWPrcadkgRuDyueXlibyE", "types": ["point_of_interest", "establishment"], "rating": 5, "user_ratings_total": 1}, "ChIJsWFkEHcbdkgRY_4GFPdi82k": {"geometry": {"location": {"lat": 51.523972, "lng": -0.169325}, "viewport": {"northeast": {"lat": 51.5253462302915, "lng": -0.168020069708498}, "southwest": {"lat": 51.5226482697085, "lng": -0.170718030291502}}}, "name": "DPD Parcel Shop Location", "place_id": "ChIJsWFkEHcbdkgRY_4GFPdi82k", "types": ["point_of_interest", "establishment"]}, "ChIJ_UdzP7cadkgR_3WO-PwuKcI": {"geometry": {"location": {"lat": 51.5239415, "lng": -0.1693606}, "viewport": {"northeast": {"lat": 51.5252904802915, "lng": -0.168011619708498}, "southwest": {"lat": 51.5225925197085, "lng": -0.170709580291502}}}, "name": "Woods Chemist", "place_id": "ChIJ_UdzP7cadkgR_3WO-PwuKcI", "types": ["pharmacy", "health", "point_of_interest", "store", "establishment"], "rating": 4.1, "user_ratings_total": 9}, "ChIJk35ZEJAbdkgRGYxS0JzVYSI": {"geometry": {"location": {"lat": 51.5238617, "lng": -0.16946}, "viewport": {"northeast": {"lat": 51.5252403302915, "lng": -0.168162719708498}, "southwest": {"lat": 51.5225423697085, "lng": -0.170860680291502}}}, "name": "Buffalo Greenwich", "place_id": "ChIJk35ZEJAbdkgRGYxS0JzVYSI", "types": ["restaurant", "food", "point_of_interest", "establishment"], "rating": 4.7, "user_ratings_total": 3}, "ChIJqbxNFbcadkgR8kE-MYKnRBU": {"geometry": {"location": {"lat": 51.5240717, "lng": -0.1690335}, "viewport": {"northeast": {"lat": 51.52541068029149, "lng": -0.167703119708498}, "southwest": {"lat": 51.52271271970849, "lng": -0.170401080291502}}}, "name": "Pari's Jewellery", "place_id": "ChIJqbxNFbcadkgR8kE-MYKnRBU", "types": ["jewelry_store", "point_of_interest", "store", "establishment"], "rating": 5, "user_ratings_total": 2}, "ChIJ2UBxQLcadkgRuYoTSFgJq5c": {"geometry": {"location": {"lat": 51.5241102, "lng": -0.1690897}, "viewport": {"northeast": {"lat": 51.52544878029149, "lng": -0.167758369708498}, "southwest": {"lat": 51.52275081970849, "lng": -0.170456330291502}}}, "name": "Carole Collier", "place_id": "ChIJ2UBxQLcadkgRuYoTSFgJq5c", "types": ["point_of_interest", "establishment"], "rating": 5, "user_ratings_total": 1}, "ChIJ5f07trkbdkgROKxdO6lY2AE": {"geometry": {"location": {"lat": 51.5238127, "lng": -0.169524}, "viewport": {"northeast": {"lat": 51.5251616802915, "lng": -0.168175019708498}, "southwest": {"lat": 51.5224637197085, "lng": -0.170872980291502}}}, "name": "blow LTD Academy", "place_id": "ChIJ5f07trkbdkgROKxdO6lY2AE", "types": ["point_of_interest", "establishment"], "rating": 5, "user_ratings_total": 5}, "ChIJu0VQFbcadkgRbtTzPxKiOLc": {"geometry": {"location": {"lat": 51.52404989999999, "lng": -0.16893}, "viewport": {"northeast": {"lat": 51.5255128802915, "lng": -0.167671119708498}, "southwest": {"lat": 51.5228149197085, "lng": -0.170369080291502}}}, "name": "Papillon Design Ltd", "place_id": "ChIJu0VQFbcadkgRbtTzPxKiOLc", "types": ["point_of_interest", "establishment"], "rating": 5, "user_ratings_total": 1}, "ChIJezU8OLcadkgRwDTve-iATdk": {"geometry": {"location": {"lat": 51.5239919, "lng": -0.1696425}, "viewport": {"northeast": {"lat": 51.5253408802915, "lng": -0.168293519708498}, "southwest": {"lat": 51.5226429197085, "lng": -0.170991480291502}}}, "name": "Nick Jones", "place_id": "ChIJezU8OLcadkgRwDTve-iATdk", "types": ["home_goods_store", "point_of_interest", "store", "establishment"], "rating": 5, "user_ratings_total": 6}, "ChIJqbxNFbcadkgRVCuGAfSUrb0": {"geometry": {"location": {"lat": 51.5240737, "lng": -0.1689183}, "viewport": {"northeast": {"lat": 51.5255316802915, "lng": -0.167659119708498}, "southwest": {"lat": 51.5228337197085, "lng": -0.170357080291502}}}, "name": "Beverley", "place_id": "ChIJqbxNFbcadkgRVCuGAfSUrb0", "types": ["home_goods_store", "point_of_interest", "store", "establishment"]}, "ChIJqbxNFbcadkgRQ9pWrnIgyJ8": {"geometry": {"location": {"lat": 51.52407299999999, "lng": -0.168917}, "viewport": {"northeast": {"lat": 51.52553133029149, "lng": -0.167659119708498}, "southwest": {"lat": 51.5228333697085, "lng": -0.170357080291502}}}, "name": "S Kluth", "place_id": "ChIJqbxNFbcadkgRQ9pWrnIgyJ8", "types": ["home_goods_store", "point_of_interest", "store", "establishment"]}, "ChIJA64cQLcadkgR9cqdTi-R_q8": {"geometry": {"location": {"lat": 51.5241422, "lng": -0.1690111}, "viewport": {"northeast": {"lat": 51.5255597302915, "lng": -0.167650869708498}, "southwest": {"lat": 51.5228617697085, "lng": -0.170348830291502}}}, "name": "Andre van Hese", "place_id": "ChIJA64cQLcadkgR9cqdTi-R_q8", "types": ["point_of_interest", "establishment"], "rating": 5, "user_ratings_total": 1}, "ChIJ334bQLcadkgR422mPj_jgMo": {"geometry": {"location": {"lat": 51.5241319, "lng": -0.168988}, "viewport": {"northeast": {"lat": 51.5255432302915, "lng": -0.167649819708498}, "southwest": {"lat": 51.5228452697085, "lng": -0.170347780291502}}}, "name": "Lauren-Nicole Boutique", "place_id": "ChIJ334bQLcadkgR422mPj_jgMo", "types": ["point_of_interest", "establishment"], "rating": 5, "user_ratings_total": 1}, "ChIJvbjABLoadkgRRUPsCMTNZdI": {"geometry": {"location": {"lat": 51.52600785004926, "lng": -0.1709582498774144}, "viewport": {"northeast": {"lat": 51.5273568302915, "lng": -0.169609269708498}, "southwest": {"lat": 51.5246588697085, "lng": -0.172307230291502}}}, "name": "120 B507", "place_id": "ChIJvbjABLoadkgRRUPsCMTNZdI", "types": ["route"]}, "ChIJpXZfbLoadkgR4OiVRJythI4": {"geometry": {"location": {"lat": 51.52612490000001, "lng": -0.1715388}, "viewport": {"northeast": {"lat": 51.5274545802915, "lng": -0.170126019708498}, "southwest": {"lat": 51.5247566197085, "lng": -0.172823980291502}}}, "name": "The Westminster Day & Employment Service", "place_id": "ChIJpXZfbLoadkgR4OiVRJythI4", "types": ["point_of_interest", "establishment"], "rating": 4, "user_ratings_total": 1}, "ChIJmWcY85AbdkgRA90fgBhmUek": {"geometry": {"location": {"lat": 51.5261055, "lng": -0.171174}, "viewport": {"northeast": {"lat": 51.5274284302915, "lng": -0.169853419708498}, "southwest": {"lat": 51.5247304697085, "lng": -0.172551380291502}}}, "name": "Pm Mel ltda", "place_id": "ChIJmWcY85AbdkgRA90fgBhmUek", "types": ["beauty_salon", "point_of_interest", "establishment"]}, "ChIJa5_aq7AadkgR6HDBzc8acNY": {"geometry": {"location": {"lat": 51.52509634190459, "lng": -0.1705741587041062}, "viewport": {"northeast": {"lat": 51.5264448302915, "lng": -0.169225819708498}, "southwest": {"lat": 51.5237468697085, "lng": -0.171923780291502}}}, "name": "27 Capland St", "place_id": "ChIJa5_aq7AadkgR6HDBzc8acNY", "types": ["route"]}, "ChIJ8RG4zOkbdkgRjOs2G0EsK1E": {"geometry": {"location": {"lat": 51.5251093, "lng": -0.1712307}, "viewport": {"northeast": {"lat": 51.5264235302915, "lng": -0.169815069708498}, "southwest": {"lat": 51.5237255697085, "lng": -0.172513030291502}}}, "name": "Aden Trading Ltd", "place_id": "ChIJ8RG4zOkbdkgRjOs2G0EsK1E", "types": ["point_of_interest", "establishment"], "rating": 5, "user_ratings_total": 1}, "ChIJF7h4prAadkgRFvxd6J3MqRQ": {"geometry": {"location": {"lat": 51.5250655, "lng": -0.1712791}, "viewport": {"northeast": {"lat": 51.5263813802915, "lng": -0.169866569708498}, "southwest": {"lat": 51.5236834197085, "lng": -0.172564530291502}}}, "name": "Fisherton Playgroup", "place_id": "ChIJF7h4prAadkgRFvxd6J3MqRQ", "types": ["point_of_interest", "establishment"], "rating": 5, "user_ratings_total": 3}, "ChIJOX-_rLAadkgRHQtOhVpYNao": {"geometry": {"location": {"lat": 51.52498110000001, "lng": -0.1705343}, "viewport": {"northeast": {"lat": 51.5263588802915, "lng": -0.169148619708498}, "southwest": {"lat": 51.5236609197085, "lng": -0.171846580291502}}}, "name": "Jordans House", "place_id": "ChIJOX-_rLAadkgRHQtOhVpYNao", "types": ["point_of_interest", "establishment"]}, "ChIJ63zyt7AadkgRz1M7bdfW4nk": {"geometry": {"location": {"lat": 51.52415258287304, "lng": -0.1709712254310429}, "viewport": {"northeast": {"lat": 51.5255038802915, "lng": -0.169624919708498}, "southwest": {"lat": 51.5228059197085, "lng": -0.172322880291502}}}, "name": "51-45 Capland St", "place_id": "ChIJ63zyt7AadkgRz1M7bdfW4nk", "types": ["route"]}}}